SPRi FPGA/rtl/bg_subtraction.v
// bg_subtraction.v — Pixel-wise background subtraction for SPRi
// Formula: diff_pixel = max(current - ref, 0)
//          dip_depth  = max(ref - current, 0)

module bg_subtraction #(
    parameter PIXEL_WIDTH = 12,     //ADC resolution
    parameter IMAGE_WIDTH = 1280    //Number of pixels per line (Position)
)(
    input  wire                     clk,
    input  wire                     rst_n,
    input  wire [PIXEL_WIDTH-1:0]   current_pixel,
    input  wire [PIXEL_WIDTH-1:0]   ref_pixel,
    input  wire                     valid_in,
    output wire                     ready_out,
    output reg  [PIXEL_WIDTH-1:0]   diff_pixel,
    output reg                      valid_out,
    output reg                      overflow_flag,
    output reg  [PIXEL_WIDTH-1:0]   dip_depth
);

    wire signed [PIXEL_WIDTH:0] diff_raw;

    assign ready_out = 1'b1;

    // 13-bit signed subtraction: {0, current} - {0, ref}
    assign diff_raw = {1'b0, current_pixel} - {1'b0, ref_pixel};

    always @(posedge clk or negedge rst_n) begin
        if (!rst_n) begin
            diff_pixel    <= {PIXEL_WIDTH{1'b0}};
            valid_out     <= 1'b0;
            overflow_flag <= 1'b0;
            dip_depth     <= {PIXEL_WIDTH{1'b0}};
        end
        else begin
            valid_out <= valid_in;

            if (valid_in) begin
                if (diff_raw[PIXEL_WIDTH]) begin
                    // Negative: current < ref (dip region)
                    diff_pixel    <= {PIXEL_WIDTH{1'b0}};
                    dip_depth     <= (~diff_raw[PIXEL_WIDTH-1:0]) + 1'b1;
                    overflow_flag <= 1'b1;
                end
                else begin
                    // Positive: current >= ref
                    diff_pixel    <= diff_raw[PIXEL_WIDTH-1:0];
                    dip_depth     <= {PIXEL_WIDTH{1'b0}};
                    overflow_flag <= 1'b0;
                end
            end
        end
    end

endmodule

SPRi FPGA/vivado/project_1/project_1.srcs/sim_1/new/bg_substraction_tb.v
// ============================================================
//  Testbench : tb_bg_subtraction
//  Tests the bg_subtraction module with 10 scenarios:
//    1.  Normal subtraction    (current > ref)
//    2.  Zero difference       (current == ref)
//    3.  Negative clamp        (current < ref)  → output must be 0
//    4.  SPR dip simulation    (realistic pixel sweep with dip)
//    5.  Extreme corners       (all 4 corner combos of 0 and 4095)
//    6.  Boundary ±1           (transitions around 0 and 4095)
//    7.  Minimal differences   (diff = +1 and diff = -1)
//    8.  Max range             (full-scale difference)
//    9.  Back-to-back stream   (continuous valid_in, no gaps)
//   10.  Reset during active   (rst_n asserted mid-transfer)
// ============================================================

`timescale 1ns / 1ps

module tb_bg_subtraction;

// ============================================================
// Parameters
// ============================================================
    parameter PIXEL_WIDTH = 12;
    parameter CLK_PERIOD  = 20;     // 50 MHz clock (20ns period)
    parameter IMAGE_WIDTH = 1024;

// ============================================================
// DUT Signals
// ============================================================
    reg                      clk;
    reg                      rst_n;
    reg  [PIXEL_WIDTH-1:0]   current_pixel;
    reg  [PIXEL_WIDTH-1:0]   ref_pixel;
    reg                      valid_in;

    wire [PIXEL_WIDTH-1:0]   diff_pixel;
    wire                     valid_out;
    wire                     ready_out;
    wire                     overflow_flag;

// ============================================================
// Test tracking
// ============================================================
    integer pass_count = 0;
    integer fail_count = 0;
    integer i;

// ============================================================
// DUT Instantiation
// ============================================================
    bg_subtraction #(
        .PIXEL_WIDTH(PIXEL_WIDTH),
        .IMAGE_WIDTH(IMAGE_WIDTH)
    ) dut (
        .clk           (clk),
        .rst_n         (rst_n),
        .current_pixel (current_pixel),
        .ref_pixel     (ref_pixel),
        .valid_in      (valid_in),
        .ready_out     (ready_out),
        .diff_pixel    (diff_pixel),
        .valid_out     (valid_out),
        .overflow_flag (overflow_flag)
    );

// ============================================================
// Clock Generation: 50 MHz
// ============================================================
    initial clk = 0;
    always #(CLK_PERIOD/2) clk = ~clk;

// ============================================================
// Task: Apply one pixel and check result
// ============================================================
    task apply_pixel;
        input [PIXEL_WIDTH-1:0] curr;
        input [PIXEL_WIDTH-1:0] ref;
        input [PIXEL_WIDTH-1:0] expected;
        input [63:0]            test_id;
        reg   [PIXEL_WIDTH-1:0] exp_clamped;
        begin
            // Expected = max(curr - ref, 0)
            exp_clamped = (curr >= ref) ? (curr - ref) : 0;

            @(posedge clk);
            #1;                         // small delay after edge
            current_pixel = curr;
            ref_pixel     = ref;
            valid_in      = 1'b1;

            @(posedge clk);             // DUT latches input here
            #1;
            valid_in = 1'b0;            // deassert after latch

            // diff_pixel and valid_out are now available (1-cycle latency)
            if (valid_out && diff_pixel === exp_clamped) begin
                $display("[PASS] Test %0d: curr=%0d ref=%0d | diff=%0d (expected=%0d)",
                          test_id, curr, ref, diff_pixel, exp_clamped);
                pass_count = pass_count + 1;
            end else begin
                $display("[FAIL] Test %0d: curr=%0d ref=%0d | diff=%0d (expected=%0d) valid_out=%b",
                          test_id, curr, ref, diff_pixel, exp_clamped, valid_out);
                fail_count = fail_count + 1;
            end
        end
    endtask

// ============================================================
// Main Test Sequence
// ============================================================
    initial begin
        // Waveform dump for GTKWave / Vivado XSim
        $dumpfile("sim/tb_bg_subtraction.vcd");
        $dumpvars(0, tb_bg_subtraction);

        $display("========================================");
        $display("  BG Subtraction Testbench Starting");
        $display("========================================");

        // Reset
        rst_n         = 1'b0;
        current_pixel = 12'd0;
        ref_pixel     = 12'd0;
        valid_in      = 1'b0;
        repeat(4) @(posedge clk);
        rst_n = 1'b1;
        @(posedge clk);

        // --------------------------------------------------
        // TEST 1: Normal subtraction (current > ref)
        // --------------------------------------------------
        $display("\n--- Test 1: Normal subtraction ---");
        apply_pixel(12'd3000, 12'd1000, 12'd2000, 1);   // expect 2000
        apply_pixel(12'd4095, 12'd100,  12'd3995, 2);   // expect 3995
        apply_pixel(12'd500,  12'd200,  12'd300,  3);   // expect 300

        // --------------------------------------------------
        // TEST 2: Zero difference
        // --------------------------------------------------
        $display("\n--- Test 2: Zero difference ---");
        apply_pixel(12'd2048, 12'd2048, 12'd0, 4);      // expect 0
        apply_pixel(12'd0,    12'd0,    12'd0, 5);      // expect 0

        // --------------------------------------------------
        // TEST 3: Negative clamp (current < ref → output = 0)
        // --------------------------------------------------
        $display("\n--- Test 3: Negative clamp (rectification) ---");
        apply_pixel(12'd100,  12'd500,  12'd0, 6);      // expect 0
        apply_pixel(12'd0,    12'd4095, 12'd0, 7);      // expect 0
        apply_pixel(12'd1000, 12'd1001, 12'd0, 8);      // expect 0

        // --------------------------------------------------
        // TEST 4: SPR Dip Simulation
        // Simulate a 64-pixel window of an SPR curve
        // Reference = flat baseline (2000 counts)
        // Sample    = SPR dip centered at pixel 32 (Gaussian-like)
        // --------------------------------------------------
        $display("\n--- Test 4: SPR Dip Simulation (64 pixels) ---");
        $display("  Reference = 2000 (flat baseline)");
        $display("  Sample    = Gaussian dip centered at pixel 32");
        $display("  Pixel | Curr | Ref  | Diff");

        begin : spr_sim
            integer pix;
            integer curr_val;
            integer ref_val;
            integer diff_val;
            integer dist;

            for (pix = 0; pix < 64; pix = pix + 1) begin
                ref_val  = 2000;

                // Simple Gaussian approximation: dip at pixel 32
                // depth = 1500 counts, width = 10 pixels
                dist = pix - 32;
                if (dist < 0) dist = -dist; // abs value

                if      (dist == 0)  curr_val = 500;
                else if (dist <= 2)  curr_val = 700;
                else if (dist <= 4)  curr_val = 1000;
                else if (dist <= 6)  curr_val = 1400;
                else if (dist <= 8)  curr_val = 1700;
                else if (dist <= 10) curr_val = 1900;
                else                 curr_val = 2000;

                diff_val = curr_val - ref_val;
                if (diff_val < 0) diff_val = 0;

                @(posedge clk);
                current_pixel = curr_val[PIXEL_WIDTH-1:0];
                ref_pixel     = ref_val[PIXEL_WIDTH-1:0];
                valid_in      = 1'b1;

                @(posedge clk);
                valid_in = 1'b0;
                #1;

                $display("  p=%02d  | %04d | %04d | %04d  overflow=%b",
                          pix, curr_val, ref_val, diff_pixel, overflow_flag);
            end
        end

        // --------------------------------------------------
        // TEST 5: Extreme Corners
        // All 4 combinations of min (0) and max (4095) inputs
        // --------------------------------------------------
        $display("\n--- Test 5: Extreme corners (0 and 4095) ---");
        apply_pixel(12'd0,    12'd0,    12'd0,    9);    // 0 - 0    = 0
        apply_pixel(12'd0,    12'd4095, 12'd0,    10);   // 0 - 4095 = clamp 0
        apply_pixel(12'd4095, 12'd0,    12'd4095, 11);   // 4095 - 0 = 4095
        apply_pixel(12'd4095, 12'd4095, 12'd0,    12);   // 4095 - 4095 = 0

        // --------------------------------------------------
        // TEST 6: Boundary ±1 Transitions
        // Values at and around the edges of the 12-bit range
        // --------------------------------------------------
        $display("\n--- Test 6: Boundary +/-1 transitions ---");
        apply_pixel(12'd1,    12'd0,    12'd1,    13);   // 1 - 0    = 1
        apply_pixel(12'd0,    12'd1,    12'd0,    14);   // 0 - 1    = clamp 0
        apply_pixel(12'd4095, 12'd4094, 12'd1,    15);   // 4095 - 4094 = 1
        apply_pixel(12'd4094, 12'd4095, 12'd0,    16);   // 4094 - 4095 = clamp 0
        apply_pixel(12'd1,    12'd1,    12'd0,    17);   // 1 - 1    = 0
        apply_pixel(12'd4094, 12'd4094, 12'd0,    18);   // 4094 - 4094 = 0

        // --------------------------------------------------
        // TEST 7: Minimal Differences (diff = +1, -1)
        // Verify single-LSB sensitivity across the range
        // --------------------------------------------------
        $display("\n--- Test 7: Minimal differences (single-LSB) ---");
        apply_pixel(12'd2,    12'd1,    12'd1,    19);   // mid-low:  2 - 1 = 1
        apply_pixel(12'd1,    12'd2,    12'd0,    20);   // mid-low:  1 - 2 = clamp 0
        apply_pixel(12'd2048, 12'd2047, 12'd1,    21);   // mid:      2048 - 2047 = 1
        apply_pixel(12'd2047, 12'd2048, 12'd0,    22);   // mid:      2047 - 2048 = clamp 0
        apply_pixel(12'd100,  12'd99,   12'd1,    23);   // low:      100 - 99 = 1
        apply_pixel(12'd99,   12'd100,  12'd0,    24);   // low:      99 - 100 = clamp 0
        apply_pixel(12'd3500, 12'd3499, 12'd1,    25);   // high:     3500 - 3499 = 1
        apply_pixel(12'd3499, 12'd3500, 12'd0,    26);   // high:     3499 - 3500 = clamp 0

        // --------------------------------------------------
        // TEST 8: Max Range (full-scale difference)
        // Largest possible positive and negative differences
        // --------------------------------------------------
        $display("\n--- Test 8: Max range differences ---");
        apply_pixel(12'd4095, 12'd0,    12'd4095, 27);   // max positive: 4095
        apply_pixel(12'd0,    12'd4095, 12'd0,    28);   // max negative: clamp 0
        apply_pixel(12'd4095, 12'd1,    12'd4094, 29);   // near-max positive: 4094
        apply_pixel(12'd1,    12'd4095, 12'd0,    30);   // near-max negative: clamp 0
        // Half-scale differences
        apply_pixel(12'd3072, 12'd1024, 12'd2048, 31);   // 3072 - 1024 = 2048
        apply_pixel(12'd1024, 12'd3072, 12'd0,    32);   // 1024 - 3072 = clamp 0

        // --------------------------------------------------
        // TEST 9: Back-to-Back Streaming
        // Continuous valid_in=1 for 16 pixels (no gaps)
        // This tests the pipeline under realistic throughput
        // --------------------------------------------------
        $display("\n--- Test 9: Back-to-back streaming (16 pixels) ---");
        begin : stream_test
            integer s;
            reg [PIXEL_WIDTH-1:0] stream_curr [0:15];
            reg [PIXEL_WIDTH-1:0] stream_ref  [0:15];
            reg [PIXEL_WIDTH-1:0] stream_exp  [0:15];
            reg [PIXEL_WIDTH-1:0] captured     [0:15];
            integer cap_idx;
            integer stream_pass;
            integer stream_fail;

            // Initialize test vectors: ramp with varying reference
            stream_curr[0]  = 12'd100;   stream_ref[0]  = 12'd50;
            stream_curr[1]  = 12'd200;   stream_ref[1]  = 12'd200;
            stream_curr[2]  = 12'd300;   stream_ref[2]  = 12'd400;
            stream_curr[3]  = 12'd4095;  stream_ref[3]  = 12'd0;
            stream_curr[4]  = 12'd0;     stream_ref[4]  = 12'd4095;
            stream_curr[5]  = 12'd2048;  stream_ref[5]  = 12'd2048;
            stream_curr[6]  = 12'd1000;  stream_ref[6]  = 12'd999;
            stream_curr[7]  = 12'd999;   stream_ref[7]  = 12'd1000;
            stream_curr[8]  = 12'd3000;  stream_ref[8]  = 12'd1500;
            stream_curr[9]  = 12'd1500;  stream_ref[9]  = 12'd3000;
            stream_curr[10] = 12'd1;     stream_ref[10] = 12'd0;
            stream_curr[11] = 12'd0;     stream_ref[11] = 12'd1;
            stream_curr[12] = 12'd4094;  stream_ref[12] = 12'd4095;
            stream_curr[13] = 12'd4095;  stream_ref[13] = 12'd4094;
            stream_curr[14] = 12'd2500;  stream_ref[14] = 12'd2500;
            stream_curr[15] = 12'd750;   stream_ref[15] = 12'd250;

            // Precompute expected values
            for (s = 0; s < 16; s = s + 1) begin
                stream_exp[s] = (stream_curr[s] >= stream_ref[s]) ?
                                (stream_curr[s] - stream_ref[s]) : 12'd0;
            end

            // Drive all 16 pixels back-to-back (valid_in=1 continuously)
            for (s = 0; s < 16; s = s + 1) begin
                @(posedge clk);
                #1;
                current_pixel = stream_curr[s];
                ref_pixel     = stream_ref[s];
                valid_in      = 1'b1;
            end

            // Deassert valid_in after last pixel
            @(posedge clk);
            #1;
            valid_in = 1'b0;

            // Wait for pipeline to flush (1 cycle latency + margin)
            @(posedge clk); #1;
            @(posedge clk); #1;

            // Capture outputs: since the DUT has 1-cycle data latency,
            // diff_pixel updates 1 cycle after each input.
            // For back-to-back, we need to re-drive and capture cycle-by-cycle.
            // Re-run with capture:
            $display("  Re-running stream with cycle-by-cycle capture...");

            cap_idx = 0;
            stream_pass = 0;
            stream_fail = 0;

            // Drive again, this time capturing outputs
            for (s = 0; s < 16; s = s + 1) begin
                @(posedge clk);
                #1;
                current_pixel = stream_curr[s];
                ref_pixel     = stream_ref[s];
                valid_in      = 1'b1;

                // After 1st cycle, previous pixel's result is available
                if (s > 0) begin
                    captured[s-1] = diff_pixel;
                end
            end

            // Capture last pixel's result
            @(posedge clk); #1;
            valid_in = 1'b0;
            captured[15] = diff_pixel;

            // Verify all captured results
            for (s = 0; s < 16; s = s + 1) begin
                if (captured[s] === stream_exp[s]) begin
                    $display("  [PASS] Stream[%02d]: curr=%04d ref=%04d | diff=%04d (exp=%04d)",
                              s, stream_curr[s], stream_ref[s], captured[s], stream_exp[s]);
                    pass_count  = pass_count + 1;
                    stream_pass = stream_pass + 1;
                end else begin
                    $display("  [FAIL] Stream[%02d]: curr=%04d ref=%04d | diff=%04d (exp=%04d)",
                              s, stream_curr[s], stream_ref[s], captured[s], stream_exp[s]);
                    fail_count  = fail_count + 1;
                    stream_fail = stream_fail + 1;
                end
            end
            $display("  Stream result: %0d passed, %0d failed", stream_pass, stream_fail);
        end

        // --------------------------------------------------
        // TEST 10: Reset During Active Operation
        // Assert reset while pipeline has valid data in-flight
        // Verify all outputs return to zero
        // --------------------------------------------------
        $display("\n--- Test 10: Reset during active operation ---");
        begin : reset_test
            reg test10_pass;
            test10_pass = 1'b1;

            // Start a valid transfer
            @(posedge clk); #1;
            current_pixel = 12'd3000;
            ref_pixel     = 12'd1000;
            valid_in      = 1'b1;

            @(posedge clk); #1;
            // Data is now latched in pipeline, assert reset
            rst_n = 1'b0;
            valid_in = 1'b0;

            // Hold reset for 2 cycles
            repeat(2) @(posedge clk);
            #1;

            // Check outputs are cleared
            if (diff_pixel !== {PIXEL_WIDTH{1'b0}}) begin
                $display("  [FAIL] Reset: diff_pixel=%0d (expected 0)", diff_pixel);
                test10_pass = 1'b0;
            end
            if (valid_out !== 1'b0) begin
                $display("  [FAIL] Reset: valid_out=%b (expected 0)", valid_out);
                test10_pass = 1'b0;
            end
            if (overflow_flag !== 1'b0) begin
                $display("  [FAIL] Reset: overflow_flag=%b (expected 0)", overflow_flag);
                test10_pass = 1'b0;
            end

            if (test10_pass) begin
                $display("  [PASS] Reset clears all outputs correctly");
                pass_count = pass_count + 1;
            end else begin
                fail_count = fail_count + 1;
            end

            // Release reset and verify module resumes correctly
            rst_n = 1'b1;
            @(posedge clk); #1;

            // Run a simple pixel after reset recovery
            $display("  Verifying post-reset operation...");
            apply_pixel(12'd2000, 12'd500, 12'd1500, 33);  // should work normally
        end

        // --------------------------------------------------
        // Results Summary
        // --------------------------------------------------
        $display("\n========================================");
        $display("  RESULTS: %0d PASSED, %0d FAILED", pass_count, fail_count);
        $display("========================================");

        if (fail_count == 0)
            $display("  ALL TESTS PASSED - Ready for ROI module");
        else
            $display("  FAILURES DETECTED - Fix before proceeding");

        $display("========================================\n");
        $finish;
    end

    // Timeout watchdog (increased for larger test suite)
    initial begin
        #200000;
        $display("[TIMEOUT] Simulation exceeded limit");
        $finish;
    end

endmodule

SPRi FPGA/sim/dump.vcd
$date
	Thu Jun 25 10:14:19 2026
$end
$version
	ModelSim Version 2020.1
$end
$timescale
	1ps
$end

$scope module tb_bg_subtraction $end
$var parameter 32 ! PIXEL_WIDTH $end
$var parameter 32 " CLK_PERIOD $end
$var parameter 32 # IMAGE_WIDTH $end
$var reg 1 $ clk $end
$var reg 1 % rst_n $end
$var reg 12 & current_pixel [11:0] $end
$var reg 12 ' ref_pixel [11:0] $end
$var reg 1 ( valid_in $end
$var wire 1 ) diff_pixel [11] $end
$var wire 1 * diff_pixel [10] $end
$var wire 1 + diff_pixel [9] $end
$var wire 1 , diff_pixel [8] $end
$var wire 1 - diff_pixel [7] $end
$var wire 1 . diff_pixel [6] $end
$var wire 1 / diff_pixel [5] $end
$var wire 1 0 diff_pixel [4] $end
$var wire 1 1 diff_pixel [3] $end
$var wire 1 2 diff_pixel [2] $end
$var wire 1 3 diff_pixel [1] $end
$var wire 1 4 diff_pixel [0] $end
$var wire 1 5 valid_out $end
$var wire 1 6 ready_out $end
$var wire 1 7 overflow_flag $end
$var integer 32 8 pass_count $end
$var integer 32 9 fail_count $end
$var integer 32 : i $end

$scope task apply_pixel $end
$var reg 12 ; curr [11:0] $end
$var reg 12 < ref [11:0] $end
$var reg 12 = expected [11:0] $end
$var reg 64 > test_id [63:0] $end
$var reg 12 ? exp_clamped [11:0] $end
$upscope $end

$scope begin spr_sim $end
$var integer 32 @ pix $end
$var integer 32 A curr_val $end
$var integer 32 B ref_val $end
$var integer 32 C diff_val $end
$var integer 32 D dist $end
$upscope $end

$scope begin stream_test $end
$var integer 32 E s $end
$var integer 32 F cap_idx $end
$var integer 32 G stream_pass $end
$var integer 32 H stream_fail $end
$upscope $end

$scope begin reset_test $end
$var reg 1 I test10_pass $end
$upscope $end

$scope module dut $end
$var parameter 32 J PIXEL_WIDTH $end
$var parameter 32 K IMAGE_WIDTH $end
$var wire 1 L clk $end
$var wire 1 M rst_n $end
$var wire 1 N current_pixel [11] $end
$var wire 1 O current_pixel [10] $end
$var wire 1 P current_pixel [9] $end
$var wire 1 Q current_pixel [8] $end
$var wire 1 R current_pixel [7] $end
$var wire 1 S current_pixel [6] $end
$var wire 1 T current_pixel [5] $end
$var wire 1 U current_pixel [4] $end
$var wire 1 V current_pixel [3] $end
$var wire 1 W current_pixel [2] $end
$var wire 1 X current_pixel [1] $end
$var wire 1 Y current_pixel [0] $end
$var wire 1 Z ref_pixel [11] $end
$var wire 1 [ ref_pixel [10] $end
$var wire 1 \ ref_pixel [9] $end
$var wire 1 ] ref_pixel [8] $end
$var wire 1 ^ ref_pixel [7] $end
$var wire 1 _ ref_pixel [6] $end
$var wire 1 ` ref_pixel [5] $end
$var wire 1 a ref_pixel [4] $end
$var wire 1 b ref_pixel [3] $end
$var wire 1 c ref_pixel [2] $end
$var wire 1 d ref_pixel [1] $end
$var wire 1 e ref_pixel [0] $end
$var wire 1 f valid_in $end
$var wire 1 6 ready_out $end
$var reg 12 g diff_pixel [11:0] $end
$var reg 1 h valid_out $end
$var reg 1 i overflow_flag $end
$var reg 12 j dip_depth [11:0] $end
$var wire 1 k diff_raw [12] $end
$var wire 1 l diff_raw [11] $end
$var wire 1 m diff_raw [10] $end
$var wire 1 n diff_raw [9] $end
$var wire 1 o diff_raw [8] $end
$var wire 1 p diff_raw [7] $end
$var wire 1 q diff_raw [6] $end
$var wire 1 r diff_raw [5] $end
$var wire 1 s diff_raw [4] $end
$var wire 1 t diff_raw [3] $end
$var wire 1 u diff_raw [2] $end
$var wire 1 v diff_raw [1] $end
$var wire 1 w diff_raw [0] $end
$upscope $end
$upscope $end
$enddefinitions $end
#0
$dumpvars
0$
0%
b0 &
b0 '
0(
b0 g
0h
0i
b0 j
bx ;
bx <
bx =
bx >
bx ?
xI
b1100 !
b10100 "
b10000000000 #
b1100 J
b10000000000 K
b0 8
b0 9
bx :
bx @
bx A
bx B
bx C
bx D
bx E
bx F
bx G
bx H
04
03
02
01
00
0/
0.
0-
0,
0+
0*
0)
05
16
07
0w
0v
0u
0t
0s
0r
0q
0p
0o
0n
0m
0l
0k
0f
0e
0d
0c
0b
0a
0`
0_
0^
0]
0\
0[
0Z
0Y
0X
0W
0V
0U
0T
0S
0R
0Q
0P
0O
0N
0M
0L
$end
#10000
1$
1L
#20000
0$
0L
#30000
1$
1L
#40000
0$
0L
#50000
1$
1L
#60000
0$
0L
#70000
1$
1L
1%
1M
#80000
0$
0L
#90000
1$
1L
b101110111000 ;
b1111101000 <
b11111010000 =
b1 >
b11111010000 ?
#100000
0$
0L
#110000
1$
1L
#111000
b101110111000 &
b1111101000 '
1(
1b
1`
1_
1^
1]
1\
1V
1U
1T
1R
1Q
1P
1N
1f
1s
1q
1p
1o
1n
1m
#120000
0$
0L
#130000
1$
1L
1h
b11111010000 g
15
10
1.
1-
1,
1+
1*
#131000
0(
b1 8
b111111111111 ;
b1100100 <
b111110011011 =
b10 >
b111110011011 ?
0f
#140000
0$
0L
#150000
1$
1L
0h
05
#151000
b111111111111 &
b1100100 '
1(
1c
0b
0^
0]
0\
1Y
1X
1W
1S
1O
1f
1w
1v
1t
0q
1l
#160000
0$
0L
#170000
1$
1L
1h
b111110011011 g
15
14
13
11
0.
1)
#171000
0(
b10 8
b111110100 ;
b11001000 <
b100101100 =
b11 >
b100101100 ?
0f
#180000
0$
0L
#190000
1$
1L
0h
05
#191000
b111110100 &
b11001000 '
1(
0c
1b
0`
1^
0Y
0X
0V
0P
0O
0N
1f
0w
0v
1u
0s
1r
0p
0n
0m
0l
#200000
0$
0L
#210000
1$
1L
1h
b100101100 g
15
04
03
12
00
1/
0-
0+
0*
0)
#211000
0(
b11 8
b100000000000 ;
b100000000000 <
b0 =
b100 >
b0 ?
0f
#220000
0$
0L
#230000
1$
1L
0h
05
#231000
b100000000000 &
b100000000000 '
1(
0b
0_
0^
1Z
0W
0U
0T
0S
0R
0Q
1N
1f
0u
0t
0r
0o
#240000
0$
0L
#250000
1$
1L
1h
b0 g
15
02
01
0/
0,
#251000
0(
b100 8
b0 ;
b0 <
b101 >
0f
#260000
0$
0L
#270000
1$
1L
0h
05
#271000
b0 &
b0 '
1(
0Z
0N
1f
#280000
0$
0L
#290000
1$
1L
1h
15
#291000
0(
b101 8
b1100100 ;
b111110100 <
b110 >
0f
#300000
0$
0L
#310000
1$
1L
0h
05
#311000
b1100100 &
b111110100 '
1(
1c
1a
1`
1_
1^
1]
1W
1T
1S
1f
1s
1r
1q
1n
1m
1l
1k
#320000
0$
0L
#330000
1$
1L
1h
b110010000 j
1i
15
17
#331000
0(
b110 8
b0 ;
b111111111111 <
b111 >
0f
#340000
0$
0L
#350000
1$
1L
0h
05
#351000
b0 &
b111111111111 '
1(
1e
1d
1b
1\
1[
1Z
0W
0T
0S
1f
1w
0s
0r
0q
0n
0m
0l
#360000
0$
0L
#370000
1$
1L
1h
b111111111111 j
15
#371000
0(
b111 8
b1111101000 ;
b1111101001 <
b1000 >
0f
#380000
0$
0L
#390000
1$
1L
0h
05
#391000
b1111101000 &
b1111101001 '
1(
0d
0c
0a
0[
0Z
1V
1T
1S
1R
1Q
1P
1f
1v
1u
1t
1s
1r
1q
1p
1o
1n
1m
1l
#400000
0$
0L
#410000
1$
1L
1h
b1 j
15
#411000
0(
b1000 8
b0 @
b11111010000 B
b11111111111111111111111111100000 D
b100000 D
b11111010000 A
b0 C
0f
#420000
0$
0L
#430000
1$
1L
b11111010000 &
b11111010000 '
1(
0e
0b
1a
0`
1[
0V
1U
0T
1O
1f
0w
0v
0u
0t
0s
0r
0q
0p
0o
0n
0m
0l
0k
0h
05
#440000
0$
0L
#450000
1$
1L
0(
0f
1h
b0 j
0i
15
07
#451000
b1 @
b11111111111111111111111111100001 D
b11111 D
#460000
0$
0L
#470000
1$
1L
1(
1f
0h
05
#480000
0$
0L
#490000
1$
1L
0(
0f
1h
15
#491000
b10 @
b11111111111111111111111111100010 D
b11110 D
#500000
0$
0L
#510000
1$
1L
1(
1f
0h
05
#520000
0$
0L
#530000
1$
1L
0(
0f
1h
15
#531000
b11 @
b11111111111111111111111111100011 D
b11101 D
#540000
0$
0L
#550000
1$
1L
1(
1f
0h
05
#560000
0$
0L
#570000
1$
1L
0(
0f
1h
15
#571000
b100 @
b11111111111111111111111111100100 D
b11100 D
#580000
0$
0L
#590000
1$
1L
1(
1f
0h
05
#600000
0$
0L
#610000
1$
1L
0(
0f
1h
15
#611000
b101 @
b11111111111111111111111111100101 D
b11011 D
#620000
0$
0L
#630000
1$
1L
1(
1f
0h
05
#640000
0$
0L
#650000
1$
1L
0(
0f
1h
15
#651000
b110 @
b11111111111111111111111111100110 D
b11010 D
#660000
0$
0L
#670000
1$
1L
1(
1f
0h
05
#680000
0$
0L
#690000
1$
1L
0(
0f
1h
15
#691000
b111 @
b11111111111111111111111111100111 D
b11001 D
#700000
0$
0L
#710000
1$
1L
1(
1f
0h
05
#720000
0$
0L
#730000
1$
1L
0(
0f
1h
15
#731000
b1000 @
b11111111111111111111111111101000 D
b11000 D
#740000
0$
0L
#750000
1$
1L
1(
1f
0h
05
#760000
0$
0L
#770000
1$
1L
0(
0f
1h
15
#771000
b1001 @
b11111111111111111111111111101001 D
b10111 D
#780000
0$
0L
#790000
1$
1L
1(
1f
0h
05
#800000
0$
0L
#810000
1$
1L
0(
0f
1h
15
#811000
b1010 @
b11111111111111111111111111101010 D
b10110 D
#820000
0$
0L
#830000
1$
1L
1(
1f
0h
05
#840000
0$
0L
#850000
1$
1L
0(
0f
1h
15
#851000
b1011 @
b11111111111111111111111111101011 D
b10101 D
#860000
0$
0L
#870000
1$
1L
1(
1f
0h
05
#880000
0$
0L
#890000
1$
1L
0(
0f
1h
15
#891000
b1100 @
b11111111111111111111111111101100 D
b10100 D
#900000
0$
0L
#910000
1$
1L
1(
1f
0h
05
#920000
0$
0L
#930000
1$
1L
0(
0f
1h
15
#931000
b1101 @
b11111111111111111111111111101101 D
b10011 D
#940000
0$
0L
#950000
1$
1L
1(
1f
0h
05
#960000
0$
0L
#970000
1$
1L
0(
0f
1h
15
#971000
b1110 @
b11111111111111111111111111101110 D
b10010 D
#980000
0$
0L
#990000
1$
1L
1(
1f
0h
05
#1000000
0$
0L
#1010000
1$
1L
0(
0f
1h
15
#1011000
b1111 @
b11111111111111111111111111101111 D
b10001 D
#1020000
0$
0L
#1030000
1$
1L
1(
1f
0h
05
#1040000
0$
0L
#1050000
1$
1L
0(
0f
1h
15
#1051000
b10000 @
b11111111111111111111111111110000 D
b10000 D
#1060000
0$
0L
#1070000
1$
1L
1(
1f
0h
05
#1080000
0$
0L
#1090000
1$
1L
0(
0f
1h
15
#1091000
b10001 @
b11111111111111111111111111110001 D
b1111 D
#1100000
0$
0L
#1110000
1$
1L
1(
1f
0h
05
#1120000
0$
0L
#1130000
1$
1L
0(
0f
1h
15
#1131000
b10010 @
b11111111111111111111111111110010 D
b1110 D
#1140000
0$
0L
#1150000
1$
1L
1(
1f
0h
05
#1160000
0$
0L
#1170000
1$
1L
0(
0f
1h
15
#1171000
b10011 @
b11111111111111111111111111110011 D
b1101 D
#1180000
0$
0L
#1190000
1$
1L
1(
1f
0h
05
#1200000
0$
0L
#1210000
1$
1L
0(
0f
1h
15
#1211000
b10100 @
b11111111111111111111111111110100 D
b1100 D
#1220000
0$
0L
#1230000
1$
1L
1(
1f
0h
05
#1240000
0$
0L
#1250000
1$
1L
0(
0f
1h
15
#1251000
b10101 @
b11111111111111111111111111110101 D
b1011 D
#1260000
0$
0L
#1270000
1$
1L
1(
1f
0h
05
#1280000
0$
0L
#1290000
1$
1L
0(
0f
1h
15
#1291000
b10110 @
b11111111111111111111111111110110 D
b1010 D
b11101101100 A
b11111111111111111111111110011100 C
b0 C
#1300000
0$
0L
#1310000
1$
1L
b11101101100 &
1(
1W
1V
0U
1T
0R
1f
1u
1t
1s
1p
1o
1n
1m
1l
1k
0h
05
#1320000
0$
0L
#1330000
1$
1L
0(
0f
1h
b1100100 j
1i
15
17
#1331000
b10111 @
b11111111111111111111111111110111 D
b1001 D
b11111111111111111111111110011100 C
b0 C
#1340000
0$
0L
#1350000
1$
1L
1(
1f
0h
05
#1360000
0$
0L
#1370000
1$
1L
0(
0f
1h
15
#1371000
b11000 @
b11111111111111111111111111111000 D
b1000 D
b11010100100 A
b11111111111111111111111011010100 C
b0 C
#1380000
0$
0L
#1390000
1$
1L
b11010100100 &
1(
0V
0S
1R
0Q
1f
0t
1q
0o
0h
05
#1400000
0$
0L
#1410000
1$
1L
0(
0f
1h
b100101100 j
15
#1411000
b11001 @
b11111111111111111111111111111001 D
b111 D
b11111111111111111111111011010100 C
b0 C
#1420000
0$
0L
#1430000
1$
1L
1(
1f
0h
05
#1440000
0$
0L
#1450000
1$
1L
0(
0f
1h
15
#1451000
b11010 @
b11111111111111111111111111111010 D
b110 D
b10101111000 A
b11111111111111111111110110101000 C
b0 C
#1460000
0$
0L
#1470000
1$
1L
b10101111000 &
1(
0W
1V
1U
1S
0R
1Q
0P
1f
0u
1t
0s
1r
0q
1o
0n
0h
05
#1480000
0$
0L
#1490000
1$
1L
0(
0f
1h
b1001011000 j
15
#1491000
b11011 @
b11111111111111111111111111111011 D
b101 D
b11111111111111111111110110101000 C
b0 C
#1500000
0$
0L
