SPRi FPGA/vivado/project_1/project_1.srcs/sources_1/new/bg_substraction.v
`timescale 1ns / 1ps
//////////////////////////////////////////////////////////////////////////////////
// Company: 
// Engineer: 
// 
// Create Date: 08.06.2026 09:33:19
// Design Name: 
// Module Name: bg_substraction
// Project Name: 
// Target Devices: 
// Tool Versions: 
// Description: 
// 
// Dependencies: 
// 
// Revision:
// Revision 0.01 - File Created
// Additional Comments:
// 
//////////////////////////////////////////////////////////////////////////////////


module bg_subtraction #(
    parameter PIXEL_WIDTH = 12,         // 12-bit pixels (S11661 sensor)
    parameter IMAGE_WIDTH = 1024        // pixels per row (from paper)
)(
    // Clock and Reset
    input  wire                     clk,
    input  wire                     rst_n,          // active low reset
    // Input: current sample frame pixel
    input  wire [PIXEL_WIDTH-1:0]   current_pixel,
    // Input: reference frame pixel (H2O baseline)
    input  wire [PIXEL_WIDTH-1:0]   ref_pixel,
    // Input handshake
    input  wire                     valid_in,       // input pixel is valid
    output wire                     ready_out,      // module ready to accept
    // Output: subtracted pixel
    output reg  [PIXEL_WIDTH-1:0]   diff_pixel,     // rectified difference
    // Output handshake
    output reg                      valid_out,      // output pixel is valid
    // Status
    output reg                      overflow_flag   // set if any pixel clipped
);
// ============================================================
// Internal signals
// ============================================================
    // One extra bit to detect sign (underflow)
    wire signed [PIXEL_WIDTH:0] diff_raw;
    // Registered valid_in to match 1-cycle output latency
    reg valid_in_r;
    // Always ready - pure combinational pipeline (1 cycle latency)
    assign ready_out = 1'b1;
    // Signed subtraction with overflow detection
    // Extended by 1 bit to catch negative result
    assign diff_raw = {1'b0, current_pixel} - {1'b0, ref_pixel};
// ============================================================
// Output Register (1 cycle latency)
// ============================================================
    always @(posedge clk or negedge rst_n) begin
        if (!rst_n) begin
            diff_pixel    <= {PIXEL_WIDTH{1'b0}};
            valid_out     <= 1'b0;
            valid_in_r    <= 1'b0;
            overflow_flag <= 1'b0;
        end
        else begin
            valid_in_r <= valid_in;         // register valid one cycle ahead
            valid_out  <= valid_in_r;       // valid_out aligns with registered output
            if (valid_in) begin
                // Rectification: clamp negative to zero
                if (diff_raw[PIXEL_WIDTH]) begin
                    // MSB = 1 means result is negative
                    diff_pixel    <= {PIXEL_WIDTH{1'b0}};   // clamp to 0
                    overflow_flag <= 1'b1;                   // flag underflow
                end
                else begin
                    diff_pixel    <= diff_raw[PIXEL_WIDTH-1:0];
                    overflow_flag <= 1'b0;
                end
            end
        end
    end
endmodule

SPRi FPGA/vivado/project_1/project_1.srcs/sim_1/new/bg_substraction_tb.v
// ============================================================
//  Testbench : tb_bg_subtraction
//  Tests the bg_subtraction module with 10 scenarios:
//    1.  Normal subtraction    (current > ref)
//    2.  Zero difference       (current == ref)
//    3.  Negative clamp        (current < ref)  → output must be 0
//    4.  SPR dip simulation    (realistic pixel sweep with dip)
//    5.  Extreme corners       (all 4 corner combos of 0 and 4095)
//    6.  Boundary ±1           (transitions around 0 and 4095)
//    7.  Minimal differences   (diff = +1 and diff = -1)
//    8.  Max range             (full-scale difference)
//    9.  Back-to-back stream   (continuous valid_in, no gaps)
//   10.  Reset during active   (rst_n asserted mid-transfer)
// ============================================================

`timescale 1ns / 1ps

module tb_bg_subtraction;

// ============================================================
// Parameters
// ============================================================
    parameter PIXEL_WIDTH = 12;
    parameter CLK_PERIOD  = 20;     // 50 MHz clock (20ns period)
    parameter IMAGE_WIDTH = 1024;

// ============================================================
// DUT Signals
// ============================================================
    reg                      clk;
    reg                      rst_n;
    reg  [PIXEL_WIDTH-1:0]   current_pixel;
    reg  [PIXEL_WIDTH-1:0]   ref_pixel;
    reg                      valid_in;

    wire [PIXEL_WIDTH-1:0]   diff_pixel;
    wire                     valid_out;
    wire                     ready_out;
    wire                     overflow_flag;

// ============================================================
// Test tracking
// ============================================================
    integer pass_count = 0;
    integer fail_count = 0;
    integer i;

// ============================================================
// DUT Instantiation
// ============================================================
    bg_subtraction #(
        .PIXEL_WIDTH(PIXEL_WIDTH),
        .IMAGE_WIDTH(IMAGE_WIDTH)
    ) dut (
        .clk           (clk),
        .rst_n         (rst_n),
        .current_pixel (current_pixel),
        .ref_pixel     (ref_pixel),
        .valid_in      (valid_in),
        .ready_out     (ready_out),
        .diff_pixel    (diff_pixel),
        .valid_out     (valid_out),
        .overflow_flag (overflow_flag)
    );

// ============================================================
// Clock Generation: 50 MHz
// ============================================================
    initial clk = 0;
    always #(CLK_PERIOD/2) clk = ~clk;

// ============================================================
// Task: Apply one pixel and check result
// ============================================================
    task apply_pixel;
        input [PIXEL_WIDTH-1:0] curr;
        input [PIXEL_WIDTH-1:0] ref;
        input [PIXEL_WIDTH-1:0] expected;
        input [63:0]            test_id;
        reg   [PIXEL_WIDTH-1:0] exp_clamped;
        begin
            // Expected = max(curr - ref, 0)
            exp_clamped = (curr >= ref) ? (curr - ref) : 0;

            @(posedge clk);
            #1;                         // small delay after edge
            current_pixel = curr;
            ref_pixel     = ref;
            valid_in      = 1'b1;

            @(posedge clk);             // DUT latches input here
            #1;
            valid_in = 1'b0;            // deassert after latch

            // diff_pixel and valid_out are now available (1-cycle latency)
            if (valid_out && diff_pixel === exp_clamped) begin
                $display("[PASS] Test %0d: curr=%0d ref=%0d | diff=%0d (expected=%0d)",
                          test_id, curr, ref, diff_pixel, exp_clamped);
                pass_count = pass_count + 1;
            end else begin
                $display("[FAIL] Test %0d: curr=%0d ref=%0d | diff=%0d (expected=%0d) valid_out=%b",
                          test_id, curr, ref, diff_pixel, exp_clamped, valid_out);
                fail_count = fail_count + 1;
            end
        end
    endtask

// ============================================================
// Main Test Sequence
// ============================================================
    initial begin
        // Waveform dump for GTKWave / Vivado XSim
        $dumpfile("sim/tb_bg_subtraction.vcd");
        $dumpvars(0, tb_bg_subtraction);

        $display("========================================");
        $display("  BG Subtraction Testbench Starting");
        $display("========================================");

        // Reset
        rst_n         = 1'b0;
        current_pixel = 12'd0;
        ref_pixel     = 12'd0;
        valid_in      = 1'b0;
        repeat(4) @(posedge clk);
        rst_n = 1'b1;
        @(posedge clk);

        // --------------------------------------------------
        // TEST 1: Normal subtraction (current > ref)
        // --------------------------------------------------
        $display("\n--- Test 1: Normal subtraction ---");
        apply_pixel(12'd3000, 12'd1000, 12'd2000, 1);   // expect 2000
        apply_pixel(12'd4095, 12'd100,  12'd3995, 2);   // expect 3995
        apply_pixel(12'd500,  12'd200,  12'd300,  3);   // expect 300

        // --------------------------------------------------
        // TEST 2: Zero difference
        // --------------------------------------------------
        $display("\n--- Test 2: Zero difference ---");
        apply_pixel(12'd2048, 12'd2048, 12'd0, 4);      // expect 0
        apply_pixel(12'd0,    12'd0,    12'd0, 5);      // expect 0

        // --------------------------------------------------
        // TEST 3: Negative clamp (current < ref → output = 0)
        // --------------------------------------------------
        $display("\n--- Test 3: Negative clamp (rectification) ---");
        apply_pixel(12'd100,  12'd500,  12'd0, 6);      // expect 0
        apply_pixel(12'd0,    12'd4095, 12'd0, 7);      // expect 0
        apply_pixel(12'd1000, 12'd1001, 12'd0, 8);      // expect 0

        // --------------------------------------------------
        // TEST 4: SPR Dip Simulation
        // Simulate a 64-pixel window of an SPR curve
        // Reference = flat baseline (2000 counts)
        // Sample    = SPR dip centered at pixel 32 (Gaussian-like)
        // --------------------------------------------------
        $display("\n--- Test 4: SPR Dip Simulation (64 pixels) ---");
        $display("  Reference = 2000 (flat baseline)");
        $display("  Sample    = Gaussian dip centered at pixel 32");
        $display("  Pixel | Curr | Ref  | Diff");

        begin : spr_sim
            integer pix;
            integer curr_val;
            integer ref_val;
            integer diff_val;
            integer dist;

            for (pix = 0; pix < 64; pix = pix + 1) begin
                ref_val  = 2000;

                // Simple Gaussian approximation: dip at pixel 32
                // depth = 1500 counts, width = 10 pixels
                dist = pix - 32;
                if (dist < 0) dist = -dist; // abs value

                if      (dist == 0)  curr_val = 500;
                else if (dist <= 2)  curr_val = 700;
                else if (dist <= 4)  curr_val = 1000;
                else if (dist <= 6)  curr_val = 1400;
                else if (dist <= 8)  curr_val = 1700;
                else if (dist <= 10) curr_val = 1900;
                else                 curr_val = 2000;

                diff_val = curr_val - ref_val;
                if (diff_val < 0) diff_val = 0;

                @(posedge clk);
                current_pixel = curr_val[PIXEL_WIDTH-1:0];
                ref_pixel     = ref_val[PIXEL_WIDTH-1:0];
                valid_in      = 1'b1;

                @(posedge clk);
                valid_in = 1'b0;
                #1;

                $display("  p=%02d  | %04d | %04d | %04d  overflow=%b",
                          pix, curr_val, ref_val, diff_pixel, overflow_flag);
            end
        end

        // --------------------------------------------------
        // TEST 5: Extreme Corners
        // All 4 combinations of min (0) and max (4095) inputs
        // --------------------------------------------------
        $display("\n--- Test 5: Extreme corners (0 and 4095) ---");
        apply_pixel(12'd0,    12'd0,    12'd0,    9);    // 0 - 0    = 0
        apply_pixel(12'd0,    12'd4095, 12'd0,    10);   // 0 - 4095 = clamp 0
        apply_pixel(12'd4095, 12'd0,    12'd4095, 11);   // 4095 - 0 = 4095
        apply_pixel(12'd4095, 12'd4095, 12'd0,    12);   // 4095 - 4095 = 0

        // --------------------------------------------------
        // TEST 6: Boundary ±1 Transitions
        // Values at and around the edges of the 12-bit range
        // --------------------------------------------------
        $display("\n--- Test 6: Boundary +/-1 transitions ---");
        apply_pixel(12'd1,    12'd0,    12'd1,    13);   // 1 - 0    = 1
        apply_pixel(12'd0,    12'd1,    12'd0,    14);   // 0 - 1    = clamp 0
        apply_pixel(12'd4095, 12'd4094, 12'd1,    15);   // 4095 - 4094 = 1
        apply_pixel(12'd4094, 12'd4095, 12'd0,    16);   // 4094 - 4095 = clamp 0
        apply_pixel(12'd1,    12'd1,    12'd0,    17);   // 1 - 1    = 0
        apply_pixel(12'd4094, 12'd4094, 12'd0,    18);   // 4094 - 4094 = 0

        // --------------------------------------------------
        // TEST 7: Minimal Differences (diff = +1, -1)
        // Verify single-LSB sensitivity across the range
        // --------------------------------------------------
        $display("\n--- Test 7: Minimal differences (single-LSB) ---");
        apply_pixel(12'd2,    12'd1,    12'd1,    19);   // mid-low:  2 - 1 = 1
        apply_pixel(12'd1,    12'd2,    12'd0,    20);   // mid-low:  1 - 2 = clamp 0
        apply_pixel(12'd2048, 12'd2047, 12'd1,    21);   // mid:      2048 - 2047 = 1
        apply_pixel(12'd2047, 12'd2048, 12'd0,    22);   // mid:      2047 - 2048 = clamp 0
        apply_pixel(12'd100,  12'd99,   12'd1,    23);   // low:      100 - 99 = 1
        apply_pixel(12'd99,   12'd100,  12'd0,    24);   // low:      99 - 100 = clamp 0
        apply_pixel(12'd3500, 12'd3499, 12'd1,    25);   // high:     3500 - 3499 = 1
        apply_pixel(12'd3499, 12'd3500, 12'd0,    26);   // high:     3499 - 3500 = clamp 0

        // --------------------------------------------------
        // TEST 8: Max Range (full-scale difference)
        // Largest possible positive and negative differences
        // --------------------------------------------------
        $display("\n--- Test 8: Max range differences ---");
        apply_pixel(12'd4095, 12'd0,    12'd4095, 27);   // max positive: 4095
        apply_pixel(12'd0,    12'd4095, 12'd0,    28);   // max negative: clamp 0
        apply_pixel(12'd4095, 12'd1,    12'd4094, 29);   // near-max positive: 4094
        apply_pixel(12'd1,    12'd4095, 12'd0,    30);   // near-max negative: clamp 0
        // Half-scale differences
        apply_pixel(12'd3072, 12'd1024, 12'd2048, 31);   // 3072 - 1024 = 2048
        apply_pixel(12'd1024, 12'd3072, 12'd0,    32);   // 1024 - 3072 = clamp 0

        // --------------------------------------------------
        // TEST 9: Back-to-Back Streaming
        // Continuous valid_in=1 for 16 pixels (no gaps)
        // This tests the pipeline under realistic throughput
        // --------------------------------------------------
        $display("\n--- Test 9: Back-to-back streaming (16 pixels) ---");
        begin : stream_test
            integer s;
            reg [PIXEL_WIDTH-1:0] stream_curr [0:15];
            reg [PIXEL_WIDTH-1:0] stream_ref  [0:15];
            reg [PIXEL_WIDTH-1:0] stream_exp  [0:15];
            reg [PIXEL_WIDTH-1:0] captured     [0:15];
            integer cap_idx;
            integer stream_pass;
            integer stream_fail;

            // Initialize test vectors: ramp with varying reference
            stream_curr[0]  = 12'd100;   stream_ref[0]  = 12'd50;
            stream_curr[1]  = 12'd200;   stream_ref[1]  = 12'd200;
            stream_curr[2]  = 12'd300;   stream_ref[2]  = 12'd400;
            stream_curr[3]  = 12'd4095;  stream_ref[3]  = 12'd0;
            stream_curr[4]  = 12'd0;     stream_ref[4]  = 12'd4095;
            stream_curr[5]  = 12'd2048;  stream_ref[5]  = 12'd2048;
            stream_curr[6]  = 12'd1000;  stream_ref[6]  = 12'd999;
            stream_curr[7]  = 12'd999;   stream_ref[7]  = 12'd1000;
            stream_curr[8]  = 12'd3000;  stream_ref[8]  = 12'd1500;
            stream_curr[9]  = 12'd1500;  stream_ref[9]  = 12'd3000;
            stream_curr[10] = 12'd1;     stream_ref[10] = 12'd0;
            stream_curr[11] = 12'd0;     stream_ref[11] = 12'd1;
            stream_curr[12] = 12'd4094;  stream_ref[12] = 12'd4095;
            stream_curr[13] = 12'd4095;  stream_ref[13] = 12'd4094;
            stream_curr[14] = 12'd2500;  stream_ref[14] = 12'd2500;
            stream_curr[15] = 12'd750;   stream_ref[15] = 12'd250;

            // Precompute expected values
            for (s = 0; s < 16; s = s + 1) begin
                stream_exp[s] = (stream_curr[s] >= stream_ref[s]) ?
                                (stream_curr[s] - stream_ref[s]) : 12'd0;
            end

            // Drive all 16 pixels back-to-back (valid_in=1 continuously)
            for (s = 0; s < 16; s = s + 1) begin
                @(posedge clk);
                #1;
                current_pixel = stream_curr[s];
                ref_pixel     = stream_ref[s];
                valid_in      = 1'b1;
            end

            // Deassert valid_in after last pixel
            @(posedge clk);
            #1;
            valid_in = 1'b0;

            // Wait for pipeline to flush (1 cycle latency + margin)
            @(posedge clk); #1;
            @(posedge clk); #1;

            // Capture outputs: since the DUT has 1-cycle data latency,
            // diff_pixel updates 1 cycle after each input.
            // For back-to-back, we need to re-drive and capture cycle-by-cycle.
            // Re-run with capture:
            $display("  Re-running stream with cycle-by-cycle capture...");

            cap_idx = 0;
            stream_pass = 0;
            stream_fail = 0;

            // Drive again, this time capturing outputs
            for (s = 0; s < 16; s = s + 1) begin
                @(posedge clk);
                #1;
                current_pixel = stream_curr[s];
                ref_pixel     = stream_ref[s];
                valid_in      = 1'b1;

                // After 1st cycle, previous pixel's result is available
                if (s > 0) begin
                    captured[s-1] = diff_pixel;
                end
            end

            // Capture last pixel's result
            @(posedge clk); #1;
            valid_in = 1'b0;
            captured[15] = diff_pixel;

            // Verify all captured results
            for (s = 0; s < 16; s = s + 1) begin
                if (captured[s] === stream_exp[s]) begin
                    $display("  [PASS] Stream[%02d]: curr=%04d ref=%04d | diff=%04d (exp=%04d)",
                              s, stream_curr[s], stream_ref[s], captured[s], stream_exp[s]);
                    pass_count  = pass_count + 1;
                    stream_pass = stream_pass + 1;
                end else begin
                    $display("  [FAIL] Stream[%02d]: curr=%04d ref=%04d | diff=%04d (exp=%04d)",
                              s, stream_curr[s], stream_ref[s], captured[s], stream_exp[s]);
                    fail_count  = fail_count + 1;
                    stream_fail = stream_fail + 1;
                end
            end
            $display("  Stream result: %0d passed, %0d failed", stream_pass, stream_fail);
        end

        // --------------------------------------------------
        // TEST 10: Reset During Active Operation
        // Assert reset while pipeline has valid data in-flight
        // Verify all outputs return to zero
        // --------------------------------------------------
        $display("\n--- Test 10: Reset during active operation ---");
        begin : reset_test
            reg test10_pass;
            test10_pass = 1'b1;

            // Start a valid transfer
            @(posedge clk); #1;
            current_pixel = 12'd3000;
            ref_pixel     = 12'd1000;
            valid_in      = 1'b1;

            @(posedge clk); #1;
            // Data is now latched in pipeline, assert reset
            rst_n = 1'b0;
            valid_in = 1'b0;

            // Hold reset for 2 cycles
            repeat(2) @(posedge clk);
            #1;

            // Check outputs are cleared
            if (diff_pixel !== {PIXEL_WIDTH{1'b0}}) begin
                $display("  [FAIL] Reset: diff_pixel=%0d (expected 0)", diff_pixel);
                test10_pass = 1'b0;
            end
            if (valid_out !== 1'b0) begin
                $display("  [FAIL] Reset: valid_out=%b (expected 0)", valid_out);
                test10_pass = 1'b0;
            end
            if (overflow_flag !== 1'b0) begin
                $display("  [FAIL] Reset: overflow_flag=%b (expected 0)", overflow_flag);
                test10_pass = 1'b0;
            end

            if (test10_pass) begin
                $display("  [PASS] Reset clears all outputs correctly");
                pass_count = pass_count + 1;
            end else begin
                fail_count = fail_count + 1;
            end

            // Release reset and verify module resumes correctly
            rst_n = 1'b1;
            @(posedge clk); #1;

            // Run a simple pixel after reset recovery
            $display("  Verifying post-reset operation...");
            apply_pixel(12'd2000, 12'd500, 12'd1500, 33);  // should work normally
        end

        // --------------------------------------------------
        // Results Summary
        // --------------------------------------------------
        $display("\n========================================");
        $display("  RESULTS: %0d PASSED, %0d FAILED", pass_count, fail_count);
        $display("========================================");

        if (fail_count == 0)
            $display("  ALL TESTS PASSED - Ready for ROI module");
        else
            $display("  FAILURES DETECTED - Fix before proceeding");

        $display("========================================\n");
        $finish;
    end

    // Timeout watchdog (increased for larger test suite)
    initial begin
        #200000;
        $display("[TIMEOUT] Simulation exceeded limit");
        $finish;
    end

endmodule

SPRi FPGA/vivado/project_1/project_1.sim/sim_1/behav/xsim/dump.vcd
$date
   Mon Jun  8 10:10:10 2026
$end

$version
  2025.2
$end

$timescale
  1ps
$end

$scope module tb_bg_subtraction $end
$var reg 1 ! clk $end
$var reg 1 " rst_n $end
$var reg 12 # current_pixel [11:0] $end
$var reg 12 $ ref_pixel [11:0] $end
$var reg 1 % valid_in $end
$var wire 12 & diff_pixel [11:0] $end
$var wire 1 ' valid_out $end
$var wire 1 ( ready_out $end
$var wire 1 ) overflow_flag $end
$var integer 32 * pass_count [31:0] $end
$var integer 32 + fail_count [31:0] $end
$var integer 32 , i [31:0] $end
$scope module dut $end
$var wire 1 - clk $end
$var wire 1 . rst_n $end
$var wire 12 / current_pixel [11:0] $end
$var wire 12 0 ref_pixel [11:0] $end
$var wire 1 1 valid_in $end
$var wire 1 ( ready_out $end
$var reg 12 2 diff_pixel [11:0] $end
$var reg 1 3 valid_out $end
$var reg 1 4 overflow_flag $end
$var wire 13 5 diff_raw [12:0] $end
$var reg 1 6 valid_in_r $end
$upscope $end
$scope begin spr_sim $end
$var integer 32 7 pix [31:0] $end
$var integer 32 8 curr_val [31:0] $end
$var integer 32 9 ref_val [31:0] $end
$var integer 32 : diff_val [31:0] $end
$var integer 32 ; dist [31:0] $end
$upscope $end
$scope begin stream_test $end
$var integer 32 < s [31:0] $end
$var integer 32 = cap_idx [31:0] $end
$var integer 32 > stream_pass [31:0] $end
$var integer 32 ? stream_fail [31:0] $end
$upscope $end
$scope begin reset_test $end
$var reg 1 @ test10_pass $end
$upscope $end
$scope task apply_pixel $end
$var reg 12 A curr [11:0] $end
$var reg 12 B ref [11:0] $end
$var reg 12 C expected [11:0] $end
$var reg 64 D test_id [63:0] $end
$var reg 12 E exp_clamped [11:0] $end
$upscope $end
$upscope $end
$enddefinitions $end

#0
$dumpvars
0!
0"
b0 #
b0 $
0%
b0 &
0'
1(
0)
b0 *
b0 +
bx ,
0-
0.
b0 /
b0 0
01
b0 2
03
04
b0 5
06
bx 7
bx 8
bx 9
bx :
bx ;
bx <
bx =
bx >
bx ?
x@
bx A
bx B
bx C
bx D
bx E
$end

#10000
1!
1-

#20000
0!
0-

#30000
1!
1-

#40000
0!
0-

#50000
1!
1-

#60000
0!
0-

#70000
1!
1"
1-
1.

#80000
0!
0-

#90000
1!
1-
b101110111000 A
b1111101000 B
b11111010000 C
b1 D
b11111010000 E

#100000
0!
0-

#110000
1!
1-

#111000
b101110111000 #
b1111101000 $
1%
b101110111000 /
b1111101000 0
11
b11111010000 5

#120000
0!
0-

#130000
1!
b11111010000 &
1-
b11111010000 2
16

#131000
0%
b1 +
01
b111111111111 A
b1100100 B
b111110011011 C
b10 D
b111110011011 E

#140000
0!
0-

#150000
1!
1'
1-
13
06

#151000
b111111111111 #
b1100100 $
1%
b111111111111 /
b1100100 0
11
b111110011011 5

#160000
0!
0-

#170000
1!
b111110011011 &
0'
1-
b111110011011 2
03
16

#171000
0%
b10 +
01
b111110100 A
b11001000 B
b100101100 C
b11 D
b100101100 E

#180000
0!
0-

#190000
1!
1'
1-
13
06

#191000
b111110100 #
b11001000 $
1%
b111110100 /
b11001000 0
11
b100101100 5

#200000
0!
0-

#210000
1!
b100101100 &
0'
1-
b100101100 2
03
16

#211000
0%
b11 +
01
b100000000000 A
b100000000000 B
b0 C
b100 D
b0 E

#220000
0!
0-

#230000
1!
1'
1-
13
06

#231000
b100000000000 #
b100000000000 $
1%
b100000000000 /
b100000000000 0
11
b0 5

#240000
0!
0-

#250000
1!
b0 &
0'
1-
b0 2
03
16

#251000
0%
b100 +
01
b0 A
b0 B
b101 D

#260000
0!
0-

#270000
1!
1'
1-
13
06

#271000
b0 #
b0 $
1%
b0 /
b0 0
11

#280000
0!
0-

#290000
1!
0'
1-
03
16

#291000
0%
b101 +
01
b1100100 A
b111110100 B
b110 D

#300000
0!
0-

#310000
1!
1'
1-
13
06

#311000
b1100100 #
b111110100 $
1%
b1100100 /
b111110100 0
11
b1111001110000 5

#320000
0!
0-

#330000
1!
0'
1)
1-
03
14
16

#331000
0%
b110 +
01
b0 A
b111111111111 B
b111 D

#340000
0!
0-

#350000
1!
1'
1-
13
06

#351000
b0 #
b111111111111 $
1%
b0 /
b111111111111 0
11
b1000000000001 5

#360000
0!
0-

#370000
1!
0'
1-
03
16

#371000
0%
b111 +
01
b1111101000 A
b1111101001 B
b1000 D

#380000
0!
0-

#390000
1!
1'
1-
13
06

#391000
b1111101000 #
b1111101001 $
1%
b1111101000 /
b1111101001 0
11
b1111111111111 5

#400000
0!
0-

#410000
1!
0'
1-
03
16

#411000
0%
b1000 +
01
b0 7
b11111010000 8
b11111010000 9
b0 :
b100000 ;

#420000
0!
0-

#430000
1!
b11111010000 #
b11111010000 $
1%
1'
1-
b11111010000 /
b11111010000 0
11
13
b0 5

#440000
0!
0-

#450000
1!
0%
1-
01
06

#451000
b1 7
b11111 ;

#460000
0!
0-

#470000
1!
1%
0'
0)
1-
11
03
04
16

#480000
0!
0-

#490000
1!
0%
1'
1-
01
13
06

#491000
b10 7
b11110 ;

#500000
0!
0-

#510000
1!
1%
0'
1-
11
03
16

#520000
0!
0-

#530000
1!
0%
1'
1-
01
13
06

#531000
b11 7
b11101 ;

#540000
0!
0-

#550000
1!
1%
0'
1-
11
03
16

#560000
0!
0-

#570000
1!
0%
1'
1-
01
13
06

#571000
b100 7
b11100 ;

#580000
0!
0-

#590000
1!
1%
0'
1-
11
03
16

#600000
0!
0-

#610000
1!
0%
1'
1-
01
13
06

#611000
b101 7
b11011 ;

#620000
0!
0-

#630000
1!
1%
0'
1-
11
03
16

#640000
0!
0-

#650000
1!
0%
1'
1-
01
13
06

#651000
b110 7
b11010 ;

#660000
0!
0-

#670000
1!
1%
0'
1-
11
03
16

#680000
0!
0-

#690000
1!
0%
1'
1-
01
13
06

#691000
b111 7
b11001 ;

#700000
0!
0-

#710000
1!
1%
0'
1-
11
03
16

#720000
0!
0-

#730000
1!
0%
1'
1-
01
13
06

#731000
b1000 7
b11000 ;

#740000
0!
0-

#750000
1!
1%
0'
1-
11
03
16

#760000
0!
0-

#770000
1!
0%
1'
1-
01
13
06

#771000
b1001 7
b10111 ;

#780000
0!
0-

#790000
1!
1%
0'
1-
11
03
16

#800000
0!
0-

#810000
1!
0%
1'
1-
01
13
06

#811000
b1010 7
b10110 ;

#820000
0!
0-

#830000
1!
1%
0'
1-
11
03
16

#840000
0!
0-

#850000
1!
0%
1'
1-
01
13
06

#851000
b1011 7
b10101 ;

#860000
0!
0-

#870000
1!
1%
0'
1-
11
03
16

#880000
0!
0-

#890000
1!
0%
1'
1-
01
13
06

#891000
b1100 7
b10100 ;

#900000
0!
0-

#910000
1!
1%
0'
1-
11
03
16

#920000
0!
0-

#930000
1!
0%
1'
1-
01
13
06

#931000
b1101 7
b10011 ;

#940000
0!
0-

#950000
1!
1%
0'
1-
11
03
16

#960000
0!
0-

#970000
1!
0%
1'
1-
01
13
06

#971000
b1110 7
b10010 ;

#980000
0!
0-

#990000
1!
1%
0'
1-
11
03
16

