SPRi FPGA/rtl/roi_centroid.v
// roi_centroid.v — Weighted centroid for SPR dip position
//
// Formula (Eq. 4):
//            Σ[ p × dip_depth[p] ]
//   p_min = ───────────────────────
//            Σ[ dip_depth[p] ]
//
// FSM: IDLE -> ACCUMULATE (1024 cyc) -> DIVIDE (32 cyc) -> DONE -> IDLE

module roi_centroid #(
    parameter PIXEL_WIDTH  = 12,        //Resolution
    parameter IMAGE_WIDTH  = 1280,      //Position
    parameter ADDR_WIDTH   = 11,        //Address Position
    parameter ACC_WIDTH    = 33,
    parameter DEN_WIDTH    = 23
)
(
    input  wire                     clk,
    input  wire                     rst_n,
    input  wire                     start,
    input  wire [PIXEL_WIDTH-1:0]   dip_depth,
    input  wire                     valid_in,
    output reg  [ADDR_WIDTH-1:0]    p_min,
    output reg                      done,
    output reg                      busy,
    output reg  [ACC_WIDTH-1:0]     dbg_numerator,
    output reg  [DEN_WIDTH-1:0]     dbg_denominator
);

    localparam IDLE       = 2'd0;
    localparam ACCUMULATE = 2'd1;
    localparam DIVIDE     = 2'd2;
    localparam DONE_ST    = 2'd3;

    reg [1:0] state;

    reg [ADDR_WIDTH-1:0]    pixel_addr;
    reg [ACC_WIDTH-1:0]     numerator;
    reg [DEN_WIDTH-1:0]     denominator;
    reg [ADDR_WIDTH-1:0]    pix_count;

    // weight = dip_depth (0 outside dip, proportional to depth inside)
    wire [PIXEL_WIDTH-1:0] weight;
    assign weight = dip_depth;

    // Sequential divider registers
    reg  [ACC_WIDTH-1:0]    div_dividend;
    reg  [DEN_WIDTH-1:0]    div_divisor;
    reg  [ACC_WIDTH-1:0]    div_quotient;
    reg  [ACC_WIDTH-1:0]    div_remainder;
    reg  [5:0]              div_count;

    always @(posedge clk or negedge rst_n) begin
        if (!rst_n) begin
            state        <= IDLE;
            pixel_addr   <= {ADDR_WIDTH{1'b0}};
            pix_count    <= {ADDR_WIDTH{1'b0}};
            numerator    <= {ACC_WIDTH{1'b0}};
            denominator  <= {DEN_WIDTH{1'b0}};
            p_min        <= {ADDR_WIDTH{1'b0}};
            done         <= 1'b0;
            busy         <= 1'b0;
            div_count    <= 6'd0;
            div_quotient <= {ACC_WIDTH{1'b0}};
            div_remainder<= {ACC_WIDTH{1'b0}};
            div_dividend <= {ACC_WIDTH{1'b0}};
            div_divisor  <= {DEN_WIDTH{1'b0}};
            dbg_numerator   <= {ACC_WIDTH{1'b0}};
            dbg_denominator <= {DEN_WIDTH{1'b0}};
        end
        else begin
            done <= 1'b0;

            case (state)

                IDLE: begin
                    busy <= 1'b0;
                    if (start) begin
                        numerator   <= {ACC_WIDTH{1'b0}};
                        denominator <= {DEN_WIDTH{1'b0}};
                        pixel_addr  <= {ADDR_WIDTH{1'b0}};
                        pix_count   <= {ADDR_WIDTH{1'b0}};
                        busy        <= 1'b1;
                        state       <= ACCUMULATE;
                    end
                end

                // numerator += p × weight, denominator += weight
                ACCUMULATE: begin
                    if (valid_in) begin
                        numerator   <= numerator
                                     + ({{(ACC_WIDTH-ADDR_WIDTH){1'b0}}, pixel_addr}
                                     *  {{(ACC_WIDTH-PIXEL_WIDTH){1'b0}}, weight});

                        denominator <= denominator
                                     + {{(DEN_WIDTH-PIXEL_WIDTH){1'b0}}, weight};

                        pixel_addr  <= pixel_addr + 1'b1;
                        pix_count   <= pix_count  + 1'b1;

                        // Last pixel: save final sums for divider
                        if (pix_count == IMAGE_WIDTH - 1) begin
                            div_dividend  <= numerator
                                           + ({{(ACC_WIDTH-ADDR_WIDTH){1'b0}}, pixel_addr}
                                           *  {{(ACC_WIDTH-PIXEL_WIDTH){1'b0}}, weight});
                            div_divisor   <= denominator
                                           + {{(DEN_WIDTH-PIXEL_WIDTH){1'b0}}, weight};

                            dbg_numerator   <= numerator
                                            + ({{(ACC_WIDTH-ADDR_WIDTH){1'b0}}, pixel_addr}
                                            *  {{(ACC_WIDTH-PIXEL_WIDTH){1'b0}}, weight});
                            dbg_denominator <= denominator
                                            + {{(DEN_WIDTH-PIXEL_WIDTH){1'b0}}, weight};

                            div_count     <= 6'd0;
                            div_quotient  <= {ACC_WIDTH{1'b0}};
                            div_remainder <= {ACC_WIDTH{1'b0}};
                            state         <= DIVIDE;
                        end
                    end
                end

                // Restoring divider: quotient = dividend / divisor (32 cycles)
                DIVIDE: begin
                    if (div_divisor == {DEN_WIDTH{1'b0}}) begin
                        p_min <= {ADDR_WIDTH{1'b0}};    // div-by-zero guard
                        state <= DONE_ST;
                    end
                    else begin
                        if ({div_remainder[ACC_WIDTH-2:0],
                             div_dividend[ACC_WIDTH-1-div_count]}
                             >= {{(ACC_WIDTH-DEN_WIDTH){1'b0}}, div_divisor})
                        begin
                            div_remainder <= {div_remainder[ACC_WIDTH-2:0],
                                              div_dividend[ACC_WIDTH-1-div_count]}
                                           - {{(ACC_WIDTH-DEN_WIDTH){1'b0}}, div_divisor};
                            div_quotient  <= {div_quotient[ACC_WIDTH-2:0], 1'b1};
                        end
                        else begin
                            div_remainder <= {div_remainder[ACC_WIDTH-2:0],
                                              div_dividend[ACC_WIDTH-1-div_count]};
                            div_quotient  <= {div_quotient[ACC_WIDTH-2:0], 1'b0};
                        end

                        div_count <= div_count + 1'b1;

                        if (div_count == ACC_WIDTH - 1)
                            state <= DONE_ST;
                    end
                end

                // p_min = quotient[9:0], pulse done
                DONE_ST: begin
                    p_min <= div_quotient[ADDR_WIDTH-1:0];
                    done  <= 1'b1;
                    busy  <= 1'b0;
                    state <= IDLE;
                end

            endcase
        end
    end

endmodule

SPRi FPGA/tb/tb_roi_centroid.v
// ============================================================
//  Testbench : tb_roi_centroid
//  Tests the roi_centroid module with basic scenarios:
//    1.  Centred spike (e.g., at pixel 500)
//    2.  Uniform dip depth (all pixels equal)
//    3.  Division by zero guard (all zeros)
// ============================================================

`timescale 1ns / 1ps

module tb_roi_centroid;

    parameter PIXEL_WIDTH  = 12;
    parameter IMAGE_WIDTH  = 1280;
    parameter ADDR_WIDTH   = 11;
    parameter ACC_WIDTH    = 33;
    parameter DEN_WIDTH    = 23;
    parameter CLK_PERIOD   = 20;     // 50 MHz

    reg                      clk;
    reg                      rst_n;
    reg                      start;
    reg  [PIXEL_WIDTH-1:0]   dip_depth;
    reg                      valid_in;

    wire [ADDR_WIDTH-1:0]    p_min;
    wire                     done;
    wire                     busy;
    wire [ACC_WIDTH-1:0]     dbg_numerator;
    wire [DEN_WIDTH-1:0]     dbg_denominator;

    integer i;
    integer pass_count = 0;
    integer fail_count = 0;

    // Instantiate DUT
    roi_centroid #(
        .PIXEL_WIDTH(PIXEL_WIDTH),
        .IMAGE_WIDTH(IMAGE_WIDTH),
        .ADDR_WIDTH(ADDR_WIDTH),
        .ACC_WIDTH(ACC_WIDTH),
        .DEN_WIDTH(DEN_WIDTH)
    ) dut (
        .clk             (clk),
        .rst_n           (rst_n),
        .start           (start),
        .dip_depth       (dip_depth),
        .valid_in        (valid_in),
        .p_min           (p_min),
        .done            (done),
        .busy            (busy),
        .dbg_numerator   (dbg_numerator),
        .dbg_denominator (dbg_denominator)
    );

    // Clock Gen
    initial clk = 0;
    always #(CLK_PERIOD/2) clk = ~clk;

    initial begin
        $dumpfile("sim/tb_roi_centroid.vcd");
        $dumpvars(0, tb_roi_centroid);

        $display("========================================");
        $display("  ROI Centroid Testbench Starting");
        $display("========================================");

        // Reset
        rst_n     = 1'b0;
        start     = 1'b0;
        dip_depth = 12'd0;
        valid_in  = 1'b0;
        repeat(5) @(posedge clk);
        rst_n = 1'b1;
        @(posedge clk);

        // --------------------------------------------------
        // TEST 1: Single Spike at Pixel 500
        // Centroid must be exactly 500
        // --------------------------------------------------
        $display("\n--- Test 1: Single spike at pixel 500 ---");
        
        @(posedge clk);
        start = 1'b1;
        @(posedge clk);
        start = 1'b0;
        
        for (i = 0; i < IMAGE_WIDTH; i = i + 1) begin
            @(posedge clk);
            #1;
            dip_depth = (i == 500) ? 12'd1000 : 12'd0;
            valid_in  = 1'b1;
        end
        
        @(posedge clk);
        #1;
        valid_in  = 1'b0;
        dip_depth = 12'd0;

        // Wait for done flag
        @(posedge clk);
        while (!done) begin
            @(posedge clk);
        end
        #1;

        if (p_min === 11'd500) begin
            $display("[PASS] Centroid correctly detected at %0d (expected 500)", p_min);
            pass_count = pass_count + 1;
        end else begin
            $display("[FAIL] Centroid detected at %0d (expected 500)", p_min);
            fail_count = fail_count + 1;
        end

        // --------------------------------------------------
        // TEST 2: Division by Zero Guard (all zeros)
        // Centroid must default to 0
        // --------------------------------------------------
        $display("\n--- Test 2: Division by Zero Guard (all zeros) ---");
        
        @(posedge clk);
        start = 1'b1;
        @(posedge clk);
        start = 1'b0;
        
        for (i = 0; i < IMAGE_WIDTH; i = i + 1) begin
            @(posedge clk);
            #1;
            dip_depth = 12'd0;
            valid_in  = 1'b1;
        end
        
        @(posedge clk);
        #1;
        valid_in  = 1'b0;

        // Wait for done flag
        @(posedge clk);
        while (!done) begin
            @(posedge clk);
        end
        #1;

        if (p_min === 11'd0) begin
            $display("[PASS] Centroid correctly defaulted to 0 on zero inputs");
            pass_count = pass_count + 1;
        end else begin
            $display("[FAIL] Centroid detected at %0d (expected 0)", p_min);
            fail_count = fail_count + 1;
        end

        // --------------------------------------------------
        // TEST 3: Uniform weights (all pixels = 10)
        // Weighted centroid = (0+1+...+1279)/1280 = 639.5 -> truncated to 639
        // --------------------------------------------------
        $display("\n--- Test 3: Uniform dip depths (all pixels = 10) ---");
        
        @(posedge clk);
        start = 1'b1;
        @(posedge clk);
        start = 1'b0;
        
        for (i = 0; i < IMAGE_WIDTH; i = i + 1) begin
            @(posedge clk);
            #1;
            dip_depth = 12'd10;
            valid_in  = 1'b1;
        end
        
        @(posedge clk);
        #1;
        valid_in  = 1'b0;

        // Wait for done flag
        @(posedge clk);
        while (!done) begin
            @(posedge clk);
        end
        #1;

        if (p_min === 11'd639 || p_min === 11'd640) begin
            $display("[PASS] Centroid correctly computed at %0d (expected ~639)", p_min);
            pass_count = pass_count + 1;
        end else begin
            $display("[FAIL] Centroid detected at %0d (expected ~639)", p_min);
            fail_count = fail_count + 1;
        end

        $display("\n========================================");
        $display("  RESULTS: %0d PASSED, %0d FAILED", pass_count, fail_count);
        $display("========================================");
        $finish;
    end

    // Watchdog
    initial begin
        #300000;
        $display("[TIMEOUT] Simulation exceeded time limit");
        $finish;
    end

endmodule

SPRi FPGA/roi_centroid/sim/dump.vcd
$date
	Mon Jun 29 01:12:36 2026
$end
$version
	ModelSim Version 2020.1
$end
$timescale
	1ps
$end

$scope module tb_roi_centroid $end
$var parameter 32 ! PIXEL_WIDTH $end
$var parameter 32 " IMAGE_WIDTH $end
$var parameter 32 # ADDR_WIDTH $end
$var parameter 32 $ ACC_WIDTH $end
$var parameter 32 % DEN_WIDTH $end
$var parameter 32 & CLK_PERIOD $end
$var reg 1 ' clk $end
$var reg 1 ( rst_n $end
$var reg 1 ) start $end
$var reg 12 * dip_depth [11:0] $end
$var reg 1 + valid_in $end
$var wire 1 , p_min [9] $end
$var wire 1 - p_min [8] $end
$var wire 1 . p_min [7] $end
$var wire 1 / p_min [6] $end
$var wire 1 0 p_min [5] $end
$var wire 1 1 p_min [4] $end
$var wire 1 2 p_min [3] $end
$var wire 1 3 p_min [2] $end
$var wire 1 4 p_min [1] $end
$var wire 1 5 p_min [0] $end
$var wire 1 6 done $end
$var wire 1 7 busy $end
$var wire 1 8 dbg_numerator [31] $end
$var wire 1 9 dbg_numerator [30] $end
$var wire 1 : dbg_numerator [29] $end
$var wire 1 ; dbg_numerator [28] $end
$var wire 1 < dbg_numerator [27] $end
$var wire 1 = dbg_numerator [26] $end
$var wire 1 > dbg_numerator [25] $end
$var wire 1 ? dbg_numerator [24] $end
$var wire 1 @ dbg_numerator [23] $end
$var wire 1 A dbg_numerator [22] $end
$var wire 1 B dbg_numerator [21] $end
$var wire 1 C dbg_numerator [20] $end
$var wire 1 D dbg_numerator [19] $end
$var wire 1 E dbg_numerator [18] $end
$var wire 1 F dbg_numerator [17] $end
$var wire 1 G dbg_numerator [16] $end
$var wire 1 H dbg_numerator [15] $end
$var wire 1 I dbg_numerator [14] $end
$var wire 1 J dbg_numerator [13] $end
$var wire 1 K dbg_numerator [12] $end
$var wire 1 L dbg_numerator [11] $end
$var wire 1 M dbg_numerator [10] $end
$var wire 1 N dbg_numerator [9] $end
$var wire 1 O dbg_numerator [8] $end
$var wire 1 P dbg_numerator [7] $end
$var wire 1 Q dbg_numerator [6] $end
$var wire 1 R dbg_numerator [5] $end
$var wire 1 S dbg_numerator [4] $end
$var wire 1 T dbg_numerator [3] $end
$var wire 1 U dbg_numerator [2] $end
$var wire 1 V dbg_numerator [1] $end
$var wire 1 W dbg_numerator [0] $end
$var wire 1 X dbg_denominator [21] $end
$var wire 1 Y dbg_denominator [20] $end
$var wire 1 Z dbg_denominator [19] $end
$var wire 1 [ dbg_denominator [18] $end
$var wire 1 \ dbg_denominator [17] $end
$var wire 1 ] dbg_denominator [16] $end
$var wire 1 ^ dbg_denominator [15] $end
$var wire 1 _ dbg_denominator [14] $end
$var wire 1 ` dbg_denominator [13] $end
$var wire 1 a dbg_denominator [12] $end
$var wire 1 b dbg_denominator [11] $end
$var wire 1 c dbg_denominator [10] $end
$var wire 1 d dbg_denominator [9] $end
$var wire 1 e dbg_denominator [8] $end
$var wire 1 f dbg_denominator [7] $end
$var wire 1 g dbg_denominator [6] $end
$var wire 1 h dbg_denominator [5] $end
$var wire 1 i dbg_denominator [4] $end
$var wire 1 j dbg_denominator [3] $end
$var wire 1 k dbg_denominator [2] $end
$var wire 1 l dbg_denominator [1] $end
$var wire 1 m dbg_denominator [0] $end
$var integer 32 n i $end
$var integer 32 o pass_count $end
$var integer 32 p fail_count $end

$scope module dut $end
$var parameter 32 q PIXEL_WIDTH $end
$var parameter 32 r IMAGE_WIDTH $end
$var parameter 32 s ADDR_WIDTH $end
$var parameter 32 t ACC_WIDTH $end
$var parameter 32 u DEN_WIDTH $end
$var parameter 2 v IDLE $end
$var parameter 2 w ACCUMULATE $end
$var parameter 2 x DIVIDE $end
$var parameter 2 y DONE_ST $end
$var wire 1 z clk $end
$var wire 1 { rst_n $end
$var wire 1 | start $end
$var wire 1 } dip_depth [11] $end
$var wire 1 ~ dip_depth [10] $end
$var wire 1 !! dip_depth [9] $end
$var wire 1 "! dip_depth [8] $end
$var wire 1 #! dip_depth [7] $end
$var wire 1 $! dip_depth [6] $end
$var wire 1 %! dip_depth [5] $end
$var wire 1 &! dip_depth [4] $end
$var wire 1 '! dip_depth [3] $end
$var wire 1 (! dip_depth [2] $end
$var wire 1 )! dip_depth [1] $end
$var wire 1 *! dip_depth [0] $end
$var wire 1 +! valid_in $end
$var reg 10 ,! p_min [9:0] $end
$var reg 1 -! done $end
$var reg 1 .! busy $end
$var reg 32 /! dbg_numerator [31:0] $end
$var reg 22 0! dbg_denominator [21:0] $end
$var reg 2 1! state [1:0] $end
$var reg 10 2! pixel_addr [9:0] $end
$var reg 32 3! numerator [31:0] $end
$var reg 22 4! denominator [21:0] $end
$var reg 10 5! pix_count [9:0] $end
$var wire 1 6! weight [11] $end
$var wire 1 7! weight [10] $end
$var wire 1 8! weight [9] $end
$var wire 1 9! weight [8] $end
$var wire 1 :! weight [7] $end
$var wire 1 ;! weight [6] $end
$var wire 1 <! weight [5] $end
$var wire 1 =! weight [4] $end
$var wire 1 >! weight [3] $end
$var wire 1 ?! weight [2] $end
$var wire 1 @! weight [1] $end
$var wire 1 A! weight [0] $end
$var reg 32 B! div_dividend [31:0] $end
$var reg 22 C! div_divisor [21:0] $end
$var reg 32 D! div_quotient [31:0] $end
$var reg 32 E! div_remainder [31:0] $end
$var reg 6 F! div_count [5:0] $end
$upscope $end
$upscope $end
$enddefinitions $end
#0
$dumpvars
0'
0(
0)
b0 *
0+
b0 ,!
0-!
0.!
b0 /!
b0 0!
b0 1!
b0 2!
b0 3!
b0 4!
b0 5!
b0 B!
b0 C!
b0 D!
b0 E!
b0 F!
b1100 !
b10000000000 "
b1010 #
b100000 $
b10110 %
b10100 &
b1100 q
b10000000000 r
b1010 s
b100000 t
b10110 u
b0 v
b1 w
b10 x
b11 y
bx n
b0 o
b0 p
05
04
03
02
01
00
0/
0.
0-
0,
06
07
0W
0V
0U
0T
0S
0R
0Q
0P
0O
0N
0M
0L
0K
0J
0I
0H
0G
0F
0E
0D
0C
0B
0A
0@
0?
0>
0=
0<
0;
0:
09
08
0m
0l
0k
0j
0i
0h
0g
0f
0e
0d
0c
0b
0a
0`
0_
0^
0]
0\
0[
0Z
0Y
0X
0A!
0@!
0?!
0>!
0=!
0<!
0;!
0:!
09!
08!
07!
06!
0+!
0*!
0)!
0(!
0'!
0&!
0%!
0$!
0#!
0"!
0!!
0~
0}
0|
0{
0z
$end
#10000
1'
1z
#20000
0'
0z
#30000
1'
1z
#40000
0'
0z
#50000
1'
1z
#60000
0'
0z
#70000
1'
1z
#80000
0'
0z
#90000
1'
1z
1(
1{
#100000
0'
0z
#110000
1'
1z
#120000
0'
0z
#130000
1'
1z
1)
1|
#140000
0'
0z
#150000
1'
1z
0)
b0 n
0|
1.!
b1 1!
17
#160000
0'
0z
#170000
1'
1z
#171000
1+
b1 n
1+!
#180000
0'
0z
#190000
1'
1z
b1 2!
b1 5!
#191000
b10 n
#200000
0'
0z
#210000
1'
1z
b10 2!
b10 5!
#211000
b11 n
#220000
0'
0z
#230000
1'
1z
b11 2!
b11 5!
#231000
b100 n
#240000
0'
0z
#250000
1'
1z
b100 2!
b100 5!
#251000
b101 n
#260000
0'
0z
#270000
1'
1z
b101 2!
b101 5!
#271000
b110 n
#280000
0'
0z
#290000
1'
1z
b110 2!
b110 5!
#291000
b111 n
#300000
0'
0z
#310000
1'
1z
b111 2!
b111 5!
#311000
b1000 n
#320000
0'
0z
#330000
1'
1z
b1000 2!
b1000 5!
#331000
b1001 n
#340000
0'
0z
#350000
1'
1z
b1001 2!
b1001 5!
#351000
b1010 n
#360000
0'
0z
#370000
1'
1z
b1010 2!
b1010 5!
#371000
b1011 n
#380000
0'
0z
#390000
1'
1z
b1011 2!
b1011 5!
#391000
b1100 n
#400000
0'
0z
#410000
1'
1z
b1100 2!
b1100 5!
#411000
b1101 n
#420000
0'
0z
#430000
1'
1z
b1101 2!
b1101 5!
#431000
b1110 n
#440000
0'
0z
#450000
1'
1z
b1110 2!
b1110 5!
#451000
b1111 n
#460000
0'
0z
#470000
1'
1z
b1111 2!
b1111 5!
#471000
b10000 n
#480000
0'
0z
#490000
1'
1z
b10000 2!
b10000 5!
#491000
b10001 n
#500000
0'
0z
#510000
1'
1z
b10001 2!
b10001 5!
#511000
b10010 n
#520000
0'
0z
#530000
1'
1z
b10010 2!
b10010 5!
#531000
b10011 n
#540000
0'
0z
#550000
1'
1z
b10011 2!
b10011 5!
#551000
b10100 n
#560000
0'
0z
#570000
1'
1z
b10100 2!
b10100 5!
#571000
b10101 n
#580000
0'
0z
#590000
1'
1z
b10101 2!
b10101 5!
#591000
b10110 n
#600000
0'
0z
#610000
1'
1z
b10110 2!
b10110 5!
#611000
b10111 n
#620000
0'
0z
#630000
1'
1z
b10111 2!
b10111 5!
#631000
b11000 n
#640000
0'
0z
#650000
1'
1z
b11000 2!
b11000 5!
#651000
b11001 n
#660000
0'
0z
#670000
1'
1z
b11001 2!
b11001 5!
#671000
b11010 n
#680000
0'
0z
#690000
1'
1z
b11010 2!
b11010 5!
#691000
b11011 n
#700000
0'
0z
#710000
1'
1z
b11011 2!
b11011 5!
#711000
b11100 n
#720000
0'
0z
#730000
1'
1z
b11100 2!
b11100 5!
#731000
b11101 n
#740000
0'
0z
#750000
1'
1z
b11101 2!
b11101 5!
#751000
b11110 n
#760000
0'
0z
#770000
1'
1z
b11110 2!
b11110 5!
#771000
b11111 n
#780000
0'
0z
#790000
1'
1z
b11111 2!
b11111 5!
#791000
b100000 n
#800000
0'
0z
#810000
1'
1z
b100000 2!
b100000 5!
#811000
b100001 n
#820000
0'
0z
#830000
1'
1z
b100001 2!
b100001 5!
#831000
b100010 n
#840000
0'
0z
#850000
1'
1z
b100010 2!
b100010 5!
#851000
b100011 n
#860000
0'
0z
#870000
1'
1z
b100011 2!
b100011 5!
#871000
b100100 n
#880000
0'
0z
#890000
1'
1z
b100100 2!
b100100 5!
#891000
b100101 n
#900000
0'
0z
#910000
1'
1z
b100101 2!
b100101 5!
#911000
b100110 n
#920000
0'
0z
#930000
1'
1z
b100110 2!
b100110 5!
#931000
b100111 n
#940000
0'
0z
#950000
1'
1z
b100111 2!
b100111 5!
#951000
b101000 n
#960000
0'
0z
#970000
1'
1z
b101000 2!
b101000 5!
#971000
b101001 n
#980000
0'
0z
#990000
1'
1z
b101001 2!
b101001 5!
#991000
b101010 n
#1000000
0'
0z
#1010000
1'
1z
b101010 2!
b101010 5!
#1011000
b101011 n
#1020000
0'
0z
#1030000
1'
1z
b101011 2!
b101011 5!
#1031000
b101100 n
#1040000
0'
0z
#1050000
1'
1z
b101100 2!
b101100 5!
#1051000
b101101 n
#1060000
0'
0z
#1070000
1'
1z
b101101 2!
b101101 5!
#1071000
b101110 n
#1080000
0'
0z
#1090000
1'
1z
b101110 2!
b101110 5!
#1091000
b101111 n
#1100000
0'
0z
#1110000
1'
1z
b101111 2!
b101111 5!
#1111000
b110000 n
#1120000
0'
0z
#1130000
1'
1z
b110000 2!
b110000 5!
#1131000
b110001 n
#1140000
0'
0z
#1150000
1'
1z
b110001 2!
b110001 5!
#1151000
b110010 n
#1160000
0'
0z
#1170000
1'
1z
b110010 2!
b110010 5!
#1171000
b110011 n
#1180000
0'
0z
#1190000
1'
1z
b110011 2!
b110011 5!
#1191000
b110100 n
#1200000
0'
0z
#1210000
1'
1z
b110100 2!
b110100 5!
#1211000
b110101 n
#1220000
0'
0z
#1230000
1'
1z
b110101 2!
b110101 5!
#1231000
b110110 n
#1240000
0'
0z
#1250000
1'
1z
b110110 2!
b110110 5!
#1251000
b110111 n
#1260000
0'
0z
#1270000
1'
1z
b110111 2!
b110111 5!
#1271000
b111000 n
#1280000
0'
0z
#1290000
1'
1z
b111000 2!
b111000 5!
#1291000
b111001 n
#1300000
0'
0z
#1310000
1'
1z
b111001 2!
b111001 5!
#1311000
b111010 n
#1320000
0'
0z
#1330000
1'
1z
b111010 2!
b111010 5!
#1331000
b111011 n
#1340000
0'
0z
#1350000
1'
1z
b111011 2!
b111011 5!
#1351000
b111100 n
#1360000
0'
0z
#1370000
1'
1z
b111100 2!
b111100 5!
#1371000
b111101 n
#1380000
0'
0z
#1390000
1'
1z
b111101 2!
b111101 5!
#1391000
b111110 n
#1400000
0'
0z
#1410000
1'
1z
b111110 2!
b111110 5!
#1411000
b111111 n
#1420000
0'
0z
#1430000
1'
1z
b111111 2!
b111111 5!
#1431000
b1000000 n
#1440000
0'
0z
#1450000
1'
1z
b1000000 2!
b1000000 5!
#1451000
b1000001 n
#1460000
0'
0z
#1470000
1'
1z
b1000001 2!
b1000001 5!
#1471000
b1000010 n
#1480000
0'
0z
#1490000
1'
1z
b1000010 2!
b1000010 5!
#1491000
b1000011 n
#1500000
0'
0z
#1510000
1'
1z
b1000011 2!
b1000011 5!
#1511000
b1000100 n
#1520000
0'
0z
#1530000
1'
1z
b1000100 2!
b1000100 5!
#1531000
b1000101 n
#1540000
0'
0z
#1550000
1'
1z
b1000101 2!
b1000101 5!
#1551000
b1000110 n
#1560000
0'
0z
#1570000
1'
1z
b1000110 2!
b1000110 5!
#1571000
b1000111 n
#1580000
0'
0z
#1590000
1'
1z
b1000111 2!
b1000111 5!
#1591000
b1001000 n
#1600000
0'
0z
#1610000
1'
1z
b1001000 2!
b1001000 5!
#1611000
b1001001 n
#1620000
0'
0z
#1630000
1'
1z
b1001001 2!
b1001001 5!
#1631000
b1001010 n
#1640000
0'
0z
#1650000
1'
1z
b1001010 2!
b1001010 5!
#1651000
b1001011 n
#1660000
0'
0z
#1670000
1'
1z
b1001011 2!
b1001011 5!
#1671000
b1001100 n
#1680000
0'
0z
#1690000
1'
1z
b1001100 2!
b1001100 5!
#1691000
b1001101 n
#1700000
0'
0z
#1710000
1'
1z
b1001101 2!
b1001101 5!
#1711000
b1001110 n
#1720000
0'
0z
#1730000
1'
1z
b1001110 2!
b1001110 5!
#1731000
b1001111 n
#1740000
0'
0z
#1750000
1'
1z
b1001111 2!
b1001111 5!
#1751000
b1010000 n
#1760000
0'
0z
#1770000
1'
1z
b1010000 2!
b1010000 5!
#1771000
b1010001 n
#1780000
0'
0z
#1790000
1'
1z
b1010001 2!
b1010001 5!
#1791000
b1010010 n
#1800000
0'
0z
#1810000
1'
1z
b1010010 2!
b1010010 5!
#1811000
b1010011 n
#1820000
0'
0z
#1830000
1'
1z
b1010011 2!
b1010011 5!
#1831000
b1010100 n
#1840000
0'
0z
#1850000
1'
1z
b1010100 2!
b1010100 5!
#1851000
b1010101 n
#1860000
0'
0z
#1870000
1'
1z
b1010101 2!
b1010101 5!
#1871000
b1010110 n
#1880000
0'
0z
#1890000
1'
1z
b1010110 2!
b1010110 5!
#1891000
b1010111 n
#1900000
0'
0z
#1910000
1'
1z
b1010111 2!
b1010111 5!
#1911000
b1011000 n
#1920000
0'
0z
#1930000
1'
1z
b1011000 2!
b1011000 5!
#1931000
b1011001 n
#1940000
0'
0z
#1950000
1'
1z
b1011001 2!
b1011001 5!
#1951000
b1011010 n
#1960000
0'
0z
#1970000
1'
1z
b1011010 2!
b1011010 5!
#1971000
b1011011 n
#1980000
0'
0z
#1990000
1'
1z
b1011011 2!
b1011011 5!
#1991000
b1011100 n
#2000000
0'
0z
#2010000
1'
1z
b1011100 2!
b1011100 5!
#2011000
b1011101 n
#2020000
0'
0z
#2030000
1'
1z
b1011101 2!
b1011101 5!
#2031000
b1011110 n
#2040000
0'
0z
#2050000
1'
1z
b1011110 2!
b1011110 5!
#2051000
b1011111 n
#2060000
0'
0z
#2070000
1'
1z
b1011111 2!
b1011111 5!
#2071000
b1100000 n
#2080000
0'
0z
#2090000
1'
1z
b1100000 2!
b1100000 5!
#2091000
b1100001 n
#2100000
0'
0z
#2110000
1'
1z
b1100001 2!
b1100001 5!
#2111000
b1100010 n
#2120000
0'
0z
#2130000
1'
1z
b1100010 2!
b1100010 5!
#2131000
b1100011 n
#2140000
0'
0z
#2150000
1'
1z
b1100011 2!
b1100011 5!
#2151000
b1100100 n
#2160000
0'
0z
#2170000
1'
1z
b1100100 2!
b1100100 5!
#2171000
b1100101 n
#2180000
0'
0z
#2190000
1'
1z
b1100101 2!
b1100101 5!
#2191000
b1100110 n
#2200000
0'
0z
#2210000
1'
1z
b1100110 2!
b1100110 5!
#2211000
b1100111 n
#2220000
0'
0z
#2230000
1'
1z
b1100111 2!
b1100111 5!
#2231000
b1101000 n
#2240000
0'
0z
#2250000
1'
1z
b1101000 2!
b1101000 5!
#2251000
b1101001 n
#2260000
0'
0z
#2270000
1'
1z
b1101001 2!
b1101001 5!
#2271000
b1101010 n
#2280000
0'
0z
#2290000
1'
1z
b1101010 2!
b1101010 5!
#2291000
b1101011 n
#2300000
0'
0z
#2310000
1'
1z
b1101011 2!
b1101011 5!
#2311000
b1101100 n
#2320000
0'
0z
#2330000
1'
1z
b1101100 2!
b1101100 5!
#2331000
b1101101 n
#2340000
0'
0z
#2350000
1'
1z
b1101101 2!
b1101101 5!
#2351000
b1101110 n
#2360000
0'
0z
#2370000
1'
1z
b1101110 2!
b1101110 5!
#2371000
b1101111 n
#2380000
0'
0z
#2390000
1'
1z
b1101111 2!
b1101111 5!
#2391000
b1110000 n
#2400000
0'
0z
#2410000
1'
1z
b1110000 2!
b1110000 5!
#2411000
b1110001 n
#2420000
0'
0z
#2430000
1'
1z
b1110001 2!
b1110001 5!
#2431000
b1110010 n
#2440000
0'
0z
#2450000
1'
1z
b1110010 2!
b1110010 5!
#2451000
b1110011 n
#2460000
0'
0z
#2470000
1'
1z
b1110011 2!
b1110011 5!
#2471000
b1110100 n
#2480000
0'
0z
#2490000
1'
1z
b1110100 2!
b1110100 5!
#2491000
b1110101 n
#2500000
0'
0z
#2510000
1'
1z
b1110101 2!
b1110101 5!
#2511000
b1110110 n
#2520000
0'
0z
#2530000
1'
1z
b1110110 2!
b1110110 5!
#2531000
b1110111 n
#2540000
0'
0z
#2550000
1'
1z
b1110111 2!
b1110111 5!
#2551000
b1111000 n
#2560000
0'
0z
#2570000
1'
1z
b1111000 2!
b1111000 5!
#2571000
b1111001 n
#2580000
0'
0z
#2590000
1'
1z
b1111001 2!
b1111001 5!
#2591000
b1111010 n
#2600000
0'
0z
#2610000
1'
1z
b1111010 2!
b1111010 5!
#2611000
b1111011 n
#2620000
0'
0z
#2630000
1'
1z
b1111011 2!
b1111011 5!
#2631000
b1111100 n
#2640000
0'
0z
#2650000
1'
1z
b1111100 2!
b1111100 5!
#2651000
b1111101 n
#2660000
0'
0z
#2670000
1'
1z
b1111101 2!
b1111101 5!
#2671000
b1111110 n
#2680000
0'
0z
#2690000
1'
1z
b1111110 2!
b1111110 5!
#2691000
b1111111 n
#2700000
0'
0z
#2710000
1'
1z
b1111111 2!
b1111111 5!
#2711000
b10000000 n
#2720000
0'
0z
#2730000
1'
1z
b10000000 2!
b10000000 5!
#2731000
b10000001 n
#2740000
0'
0z
#2750000
1'
1z
b10000001 2!
b10000001 5!
#2751000
b10000010 n
#2760000
0'
0z
#2770000
1'
1z
b10000010 2!
b10000010 5!
#2771000
b10000011 n
#2780000
0'
0z
#2790000
1'
1z
b10000011 2!
b10000011 5!
#2791000
b10000100 n
#2800000
0'
0z
#2810000
1'
1z
b10000100 2!
b10000100 5!
#2811000
b10000101 n
#2820000
0'
0z
