SPRi FPGA/rtl/roi_centroid.v
// roi_centroid.v — Weighted centroid for SPR dip position
//
// Formula (Eq. 4):
//            Σ[ p × dip_depth[p] ]
//   p_min = ───────────────────────
//            Σ[ dip_depth[p] ]
//
// FSM: IDLE -> ACCUMULATE (1024 cyc) -> DIVIDE (32 cyc) -> DONE -> IDLE

module roi_centroid #(
    parameter PIXEL_WIDTH  = 12,        //Resolution
    parameter IMAGE_WIDTH  = 1280,      //Position
    parameter ADDR_WIDTH   = 11,        //Address Position
    parameter ACC_WIDTH    = 33,
    parameter DEN_WIDTH    = 23
)
(
    input  wire                     clk,
    input  wire                     rst_n,
    input  wire                     start,
    input  wire [PIXEL_WIDTH-1:0]   dip_depth,
    input  wire                     valid_in,
    output reg  [ADDR_WIDTH-1:0]    p_min,
    output reg                      done,
    output reg                      busy,
    output reg  [ACC_WIDTH-1:0]     dbg_numerator,
    output reg  [DEN_WIDTH-1:0]     dbg_denominator
);

    localparam IDLE       = 2'd0;
    localparam ACCUMULATE = 2'd1;
    localparam DIVIDE     = 2'd2;
    localparam DONE_ST    = 2'd3;

    reg [1:0] state;

    reg [ADDR_WIDTH-1:0]    pixel_addr;
    reg [ACC_WIDTH-1:0]     numerator;
    reg [DEN_WIDTH-1:0]     denominator;
    reg [ADDR_WIDTH-1:0]    pix_count;

    // weight = dip_depth (0 outside dip, proportional to depth inside)
    wire [PIXEL_WIDTH-1:0] weight;
    assign weight = dip_depth;

    // Sequential divider registers
    reg  [ACC_WIDTH-1:0]    div_dividend;
    reg  [DEN_WIDTH-1:0]    div_divisor;
    reg  [ACC_WIDTH-1:0]    div_quotient;
    reg  [ACC_WIDTH-1:0]    div_remainder;
    reg  [5:0]              div_count;

    always @(posedge clk or negedge rst_n) begin
        if (!rst_n) begin
            state        <= IDLE;
            pixel_addr   <= {ADDR_WIDTH{1'b0}};
            pix_count    <= {ADDR_WIDTH{1'b0}};
            numerator    <= {ACC_WIDTH{1'b0}};
            denominator  <= {DEN_WIDTH{1'b0}};
            p_min        <= {ADDR_WIDTH{1'b0}};
            done         <= 1'b0;
            busy         <= 1'b0;
            div_count    <= 6'd0;
            div_quotient <= {ACC_WIDTH{1'b0}};
            div_remainder<= {ACC_WIDTH{1'b0}};
            div_dividend <= {ACC_WIDTH{1'b0}};
            div_divisor  <= {DEN_WIDTH{1'b0}};
            dbg_numerator   <= {ACC_WIDTH{1'b0}};
            dbg_denominator <= {DEN_WIDTH{1'b0}};
        end
        else begin
            done <= 1'b0;

            case (state)

                IDLE: begin
                    busy <= 1'b0;
                    if (start) begin
                        numerator   <= {ACC_WIDTH{1'b0}};
                        denominator <= {DEN_WIDTH{1'b0}};
                        pixel_addr  <= {ADDR_WIDTH{1'b0}};
                        pix_count   <= {ADDR_WIDTH{1'b0}};
                        busy        <= 1'b1;
                        state       <= ACCUMULATE;
                    end
                end

                // numerator += p × weight, denominator += weight
                ACCUMULATE: begin
                    if (valid_in) begin
                        numerator   <= numerator
                                     + ({{(ACC_WIDTH-ADDR_WIDTH){1'b0}}, pixel_addr}
                                     *  {{(ACC_WIDTH-PIXEL_WIDTH){1'b0}}, weight});

                        denominator <= denominator
                                     + {{(DEN_WIDTH-PIXEL_WIDTH){1'b0}}, weight};

                        pixel_addr  <= pixel_addr + 1'b1;
                        pix_count   <= pix_count  + 1'b1;

                        // Last pixel: save final sums for divider
                        if (pix_count == IMAGE_WIDTH - 1) begin
                            div_dividend  <= numerator
                                           + ({{(ACC_WIDTH-ADDR_WIDTH){1'b0}}, pixel_addr}
                                           *  {{(ACC_WIDTH-PIXEL_WIDTH){1'b0}}, weight});
                            div_divisor   <= denominator
                                           + {{(DEN_WIDTH-PIXEL_WIDTH){1'b0}}, weight};

                            dbg_numerator   <= numerator
                                            + ({{(ACC_WIDTH-ADDR_WIDTH){1'b0}}, pixel_addr}
                                            *  {{(ACC_WIDTH-PIXEL_WIDTH){1'b0}}, weight});
                            dbg_denominator <= denominator
                                            + {{(DEN_WIDTH-PIXEL_WIDTH){1'b0}}, weight};

                            div_count     <= 6'd0;
                            div_quotient  <= {ACC_WIDTH{1'b0}};
                            div_remainder <= {ACC_WIDTH{1'b0}};
                            state         <= DIVIDE;
                        end
                    end
                end

                // Restoring divider: quotient = dividend / divisor (32 cycles)
                DIVIDE: begin
                    if (div_divisor == {DEN_WIDTH{1'b0}}) begin
                        p_min <= {ADDR_WIDTH{1'b0}};    // div-by-zero guard
                        state <= DONE_ST;
                    end
                    else begin
                        if ({div_remainder[ACC_WIDTH-2:0],
                             div_dividend[ACC_WIDTH-1-div_count]}
                             >= {{(ACC_WIDTH-DEN_WIDTH){1'b0}}, div_divisor})
                        begin
                            div_remainder <= {div_remainder[ACC_WIDTH-2:0],
                                              div_dividend[ACC_WIDTH-1-div_count]}
                                           - {{(ACC_WIDTH-DEN_WIDTH){1'b0}}, div_divisor};
                            div_quotient  <= {div_quotient[ACC_WIDTH-2:0], 1'b1};
                        end
                        else begin
                            div_remainder <= {div_remainder[ACC_WIDTH-2:0],
                                              div_dividend[ACC_WIDTH-1-div_count]};
                            div_quotient  <= {div_quotient[ACC_WIDTH-2:0], 1'b0};
                        end

                        div_count <= div_count + 1'b1;

                        if (div_count == ACC_WIDTH - 1)
                            state <= DONE_ST;
                    end
                end

                // p_min = quotient[9:0], pulse done
                DONE_ST: begin
                    p_min <= div_quotient[ADDR_WIDTH-1:0];
                    done  <= 1'b1;
                    busy  <= 1'b0;
                    state <= IDLE;
                end

            endcase
        end
    end

endmodule

SPRi FPGA/rtl/bg_subtraction.v
// bg_subtraction.v — Pixel-wise background subtraction for SPRi
// Formula: diff_pixel = max(current - ref, 0)
//          dip_depth  = max(ref - current, 0)

module bg_subtraction #(
    parameter PIXEL_WIDTH = 12,     //ADC resolution
    parameter IMAGE_WIDTH = 1280    //Number of pixels per line (Position)
)(
    input  wire                     clk,
    input  wire                     rst_n,
    input  wire [PIXEL_WIDTH-1:0]   current_pixel,
    input  wire [PIXEL_WIDTH-1:0]   ref_pixel,
    input  wire                     valid_in,
    output wire                     ready_out,
    output reg  [PIXEL_WIDTH-1:0]   diff_pixel,
    output reg                      valid_out,
    output reg                      overflow_flag,
    output reg  [PIXEL_WIDTH-1:0]   dip_depth
);

    wire signed [PIXEL_WIDTH:0] diff_raw;

    assign ready_out = 1'b1;

    // 13-bit signed subtraction: {0, current} - {0, ref}
    assign diff_raw = {1'b0, current_pixel} - {1'b0, ref_pixel};

    always @(posedge clk or negedge rst_n) begin
        if (!rst_n) begin
            diff_pixel    <= {PIXEL_WIDTH{1'b0}};
            valid_out     <= 1'b0;
            overflow_flag <= 1'b0;
            dip_depth     <= {PIXEL_WIDTH{1'b0}};
        end
        else begin
            valid_out <= valid_in;

            if (valid_in) begin
                if (diff_raw[PIXEL_WIDTH]) begin
                    // Negative: current < ref (dip region)
                    diff_pixel    <= {PIXEL_WIDTH{1'b0}};
                    dip_depth     <= (~diff_raw[PIXEL_WIDTH-1:0]) + 1'b1;
                    overflow_flag <= 1'b1;
                end
                else begin
                    // Positive: current >= ref
                    diff_pixel    <= diff_raw[PIXEL_WIDTH-1:0];
                    dip_depth     <= {PIXEL_WIDTH{1'b0}};
                    overflow_flag <= 1'b0;
                end
            end
        end
    end

endmodule

SPRi FPGA/ip_repo/spr_accel_axi_1.0/src/spr_pipeline.v
// spr_pipeline.v — Top-level pipeline wrapper for SPRi processing
// Combines bg_subtraction and roi_centroid modules.

`timescale 1ns / 1ps

module spr_pipeline #(
    parameter PIXEL_WIDTH  = 12,
    parameter IMAGE_WIDTH  = 1280,
    parameter ADDR_WIDTH   = 11,
    parameter ACC_WIDTH    = 33,
    parameter DEN_WIDTH    = 23
)(
    input  wire                     clk,
    input  wire                     rst_n,
    
    // Control
    input  wire                     start_frame,    // pulse to start a new frame
    
    // Input Stream (from sensor/ADC)
    input  wire [PIXEL_WIDTH-1:0]   current_pixel,
    input  wire [PIXEL_WIDTH-1:0]   ref_pixel,
    input  wire                     valid_in,
    output wire                     ready_out,
    
    // Output Result (Centroid)
    output wire [ADDR_WIDTH-1:0]    p_min,
    output wire                     done,
    output wire                     busy,
    
    // Debug / Monitoring
    output wire [PIXEL_WIDTH-1:0]   diff_pixel,
    output wire                     valid_out_pixel,
    output wire                     overflow_flag,
    output wire [ACC_WIDTH-1:0]     dbg_numerator,
    output wire [DEN_WIDTH-1:0]     dbg_denominator
);

    wire [PIXEL_WIDTH-1:0]   bg_dip_depth;
    wire                     bg_valid_out;

    // Instantiate Stage 1: Background Subtraction
    bg_subtraction #(
        .PIXEL_WIDTH(PIXEL_WIDTH),
        .IMAGE_WIDTH(IMAGE_WIDTH)
    ) u_bg_sub (
        .clk           (clk),
        .rst_n         (rst_n),
        .current_pixel (current_pixel),
        .ref_pixel     (ref_pixel),
        .valid_in      (valid_in),
        .ready_out     (ready_out),
        .diff_pixel    (diff_pixel),
        .valid_out     (bg_valid_out),
        .overflow_flag (overflow_flag),
        .dip_depth     (bg_dip_depth)
    );

    assign valid_out_pixel = bg_valid_out;

    // Instantiate Stage 2: ROI Centroid Calculator
    roi_centroid #(
        .PIXEL_WIDTH(PIXEL_WIDTH),
        .IMAGE_WIDTH(IMAGE_WIDTH),
        .ADDR_WIDTH(ADDR_WIDTH),
        .ACC_WIDTH(ACC_WIDTH),
        .DEN_WIDTH(DEN_WIDTH)
    ) u_centroid (
        .clk             (clk),
        .rst_n           (rst_n),
        .start           (start_frame),
        .dip_depth       (bg_dip_depth),
        .valid_in        (bg_valid_out),
        .p_min           (p_min),
        .done            (done),
        .busy            (busy),
        .dbg_numerator   (dbg_numerator),
        .dbg_denominator (dbg_denominator)
    );

endmodule

SPRi FPGA/ip_repo/spr_accel_axi_1.0/src/tb_spr_pipeline.v
// ============================================================
//  Testbench : tb_spr_pipeline
//  Tests the full SPR processing pipeline (Stage 1 + Stage 2):
//    1. Instantiates spr_pipeline.v
//    2. Generates a realistic Gaussian SPR dip (centered at pixel 512)
//    3. Streams the pixels into the background subtraction block
//    4. Feeds the resulting dip depths to the centroid accumulator
//    5. Monitors the sequential divider and verifies the final p_min output.
// ============================================================

`timescale 1ns / 1ps

module tb_spr_pipeline;

    parameter PIXEL_WIDTH  = 12;
    parameter IMAGE_WIDTH  = 1280;
    parameter ADDR_WIDTH   = 11;
    parameter ACC_WIDTH    = 33;
    parameter DEN_WIDTH    = 23;
    parameter CLK_PERIOD   = 20;     // 50 MHz

    reg                      clk;
    reg                      rst_n;
    reg                      start_frame;
    reg  [PIXEL_WIDTH-1:0]   current_pixel;
    reg  [PIXEL_WIDTH-1:0]   ref_pixel;
    reg                      valid_in;

    wire [ADDR_WIDTH-1:0]    p_min;
    wire                     done;
    wire                     busy;

    wire [PIXEL_WIDTH-1:0]   diff_pixel;
    wire                     valid_out_pixel;
    wire                     overflow_flag;
    wire [ACC_WIDTH-1:0]     dbg_numerator;
    wire [DEN_WIDTH-1:0]     dbg_denominator;

    integer i;
    real    dist, val;
    integer curr_val;
    integer ref_val;

    // Instantiate Full Pipeline DUT
    spr_pipeline #(
        .PIXEL_WIDTH(PIXEL_WIDTH),
        .IMAGE_WIDTH(IMAGE_WIDTH),
        .ADDR_WIDTH(ADDR_WIDTH),
        .ACC_WIDTH(ACC_WIDTH),
        .DEN_WIDTH(DEN_WIDTH)
    ) dut (
        .clk             (clk),
        .rst_n           (rst_n),
        .start_frame     (start_frame),
        .current_pixel   (current_pixel),
        .ref_pixel       (ref_pixel),
        .valid_in        (valid_in),
        .ready_out       (), // unconnected
        .p_min           (p_min),
        .done            (done),
        .busy            (busy),
        .diff_pixel      (diff_pixel),
        .valid_out_pixel (valid_out_pixel),
        .overflow_flag   (overflow_flag),
        .dbg_numerator   (dbg_numerator),
        .dbg_denominator (dbg_denominator)
    );

    // Clock Gen
    initial clk = 0;
    always #(CLK_PERIOD/2) clk = ~clk;

    initial begin
        $dumpfile("sim/tb_spr_pipeline.vcd");
        $dumpvars(0, tb_spr_pipeline);

        $display("========================================");
        $display("  Full SPR Pipeline Testbench Starting");
        $display("  Sensor Size: %0d pixels | ADC: %0d-bit", IMAGE_WIDTH, PIXEL_WIDTH);
        $display("========================================");

        // Reset
        rst_n       = 1'b0;
        start_frame = 1'b0;
        current_pixel = 12'd0;
        ref_pixel     = 12'd0;
        valid_in      = 1'b0;
        repeat(5) @(posedge clk);
        rst_n = 1'b1;
        @(posedge clk);

        // --------------------------------------------------
        // TEST: Gaussian Dip centred at pixel 512
        // Baseline = 2800 counts, depth = 2000 counts, sigma = 40
        // --------------------------------------------------
        $display("\n--- Starting SPR Frame Simulation ---");
        $display("  Simulating Gaussian dip at pixel 512...");

        @(posedge clk);
        start_frame = 1'b1;
        @(posedge clk);
        start_frame = 1'b0;

        for (i = 0; i < IMAGE_WIDTH; i = i + 1) begin
            // Baseline reference is flat at 2800 counts
            ref_val = 2800;

            // Generate Gaussian dip
            dist = i - 512;
            val = 2800.0 - 2000.0 * $exp(-0.5 * (dist / 40.0) * (dist / 40.0));
            curr_val = $rtoi(val);

            // Clip outputs to valid 12-bit ADC range
            if (curr_val < 0) curr_val = 0;
            if (curr_val > 4095) curr_val = 4095;

            @(posedge clk);
            #1;
            current_pixel = curr_val[PIXEL_WIDTH-1:0];
            ref_pixel     = ref_val[PIXEL_WIDTH-1:0];
            valid_in      = 1'b1;

            // Display a few samples around the dip center for logging
            if (i >= 508 && i <= 516) begin
                $display("  Pixel %0d: sample=%0d, ref=%0d, diff=%0d, overflow=%b (latency corrected)", 
                         i-1, current_pixel, ref_pixel, diff_pixel, overflow_flag);
            end
        end

        @(posedge clk);
        #1;
        valid_in      = 1'b0;
        current_pixel = 12'd0;
        ref_pixel     = 12'd0;

        $display("  Frame streamed in. Waiting for division & centroid completion...");

        // Wait for Done
        @(posedge clk);
        while (!done) begin
            @(posedge clk);
        end
        #1;

        $display("\n========================================");
        $display("  Pipeline Execution Completed");
        $display("  RTL Centroid p_min: %0d", p_min);
        $display("  Numerator sum:      %0d", dbg_numerator);
        $display("  Denominator sum:    %0d", dbg_denominator);
        $display("========================================");

        // Verification: true center was 512, acceptable integer division error is +/- 1 pixel
        if (p_min >= 11'd511 && p_min <= 11'd513) begin
            $display("[PASS] Centroid matches expected true center (512) within tolerance!");
        end else begin
            $display("[FAIL] Centroid is off! Expected ~512, Got %0d", p_min);
        end
        $display("========================================\n");

        $finish;
    end

    // Watchdog Timeout
    initial begin
        #300000;
        $display("[TIMEOUT] Simulation timed out");
        $finish;
    end

endmodule

SPRi FPGA/Project_1/SPRi/SPRi.sim/sim_1/behav/xsim/dump.vcd
$date
   Mon Jun 29 01:33:16 2026
$end

$version
  2025.2
$end

$timescale
  1ps
$end

$scope module tb_spr_pipeline $end
$var reg 1 ! clk $end
$var reg 1 " rst_n $end
$var reg 1 # start_frame $end
$var reg 12 $ current_pixel [11:0] $end
$var reg 12 % ref_pixel [11:0] $end
$var reg 1 & valid_in $end
$var wire 10 ' p_min [9:0] $end
$var wire 1 ( done $end
$var wire 1 ) busy $end
$var wire 12 * diff_pixel [11:0] $end
$var wire 1 + valid_out_pixel $end
$var wire 1 , overflow_flag $end
$var wire 32 - dbg_numerator [31:0] $end
$var wire 22 . dbg_denominator [21:0] $end
$var integer 32 / i [31:0] $end
$var real 32 0 dist $end
$var real 32 1 val $end
$var integer 32 2 curr_val [31:0] $end
$var integer 32 3 ref_val [31:0] $end
$scope module dut $end
$var wire 1 4 clk $end
$var wire 1 5 rst_n $end
$var wire 1 6 start_frame $end
$var wire 12 7 current_pixel [11:0] $end
$var wire 12 8 ref_pixel [11:0] $end
$var wire 1 9 valid_in $end
$var wire 1 : ready_out $end
$var wire 10 ' p_min [9:0] $end
$var wire 1 ( done $end
$var wire 1 ) busy $end
$var wire 12 * diff_pixel [11:0] $end
$var wire 1 + valid_out_pixel $end
$var wire 1 , overflow_flag $end
$var wire 32 - dbg_numerator [31:0] $end
$var wire 22 . dbg_denominator [21:0] $end
$var wire 12 ; bg_dip_depth [11:0] $end
$var wire 1 < bg_valid_out $end
$scope module u_bg_sub $end
$var wire 1 4 clk $end
$var wire 1 5 rst_n $end
$var wire 12 7 current_pixel [11:0] $end
$var wire 12 8 ref_pixel [11:0] $end
$var wire 1 9 valid_in $end
$var wire 1 : ready_out $end
$var reg 12 = diff_pixel [11:0] $end
$var reg 1 > valid_out $end
$var reg 1 ? overflow_flag $end
$var reg 12 @ dip_depth [11:0] $end
$var wire 13 A diff_raw [12:0] $end
$upscope $end
$scope module u_centroid $end
$var wire 1 4 clk $end
$var wire 1 5 rst_n $end
$var wire 1 6 start $end
$var wire 12 ; dip_depth [11:0] $end
$var wire 1 < valid_in $end
$var reg 10 B p_min [9:0] $end
$var reg 1 C done $end
$var reg 1 D busy $end
$var reg 32 E dbg_numerator [31:0] $end
$var reg 22 F dbg_denominator [21:0] $end
$var reg 2 G state [1:0] $end
$var reg 10 H pixel_addr [9:0] $end
$var reg 32 I numerator [31:0] $end
$var reg 22 J denominator [21:0] $end
$var reg 10 K pix_count [9:0] $end
$var wire 12 L weight [11:0] $end
$var reg 32 M div_dividend [31:0] $end
$var reg 22 N div_divisor [21:0] $end
$var reg 32 O div_quotient [31:0] $end
$var reg 32 P div_remainder [31:0] $end
$var reg 6 Q div_count [5:0] $end
$upscope $end
$upscope $end
$upscope $end
$enddefinitions $end

#0
$dumpvars
0!
0"
0#
b0 $
b0 %
0&
b0 '
0(
0)
b0 *
0+
0,
b0 -
b0 .
bx /
r0 0
r0 1
bx 2
bx 3
04
05
06
b0 7
b0 8
09
1:
b0 ;
0<
b0 =
0>
0?
b0 @
b0 A
b0 B
0C
0D
b0 E
b0 F
b0 G
b0 H
b0 I
b0 J
b0 K
b0 L
b0 M
b0 N
b0 O
b0 P
b0 Q
$end

#10000
1!
14

#20000
0!
04

#30000
1!
14

#40000
0!
04

#50000
1!
14

#60000
0!
04

#70000
1!
14

#80000
0!
04

#90000
1!
1"
14
15

#100000
0!
04

#110000
1!
14

#120000
0!
04

#130000
1!
1#
1)
14
16
1D
b1 G

#140000
0!
04

#150000
1!
0#
b0 /
r-512 0
r2800 1
b101011110000 2
b101011110000 3
14
06

#160000
0!
04

#170000
1!
14

#171000
b101011110000 $
b101011110000 %
1&
b1 /
r-511 0
b101011110000 7
b101011110000 8
19

#180000
0!
04

#190000
1!
1+
14
1<
1>

#191000
b10 /
r-510 0

#200000
0!
04

#210000
1!
14
b1 H
b1 K

#211000
b11 /
r-509 0

#220000
0!
04

#230000
1!
14
b10 H
b10 K

#231000
b100 /
r-508 0

#240000
0!
04

#250000
1!
14
b11 H
b11 K

#251000
b101 /
r-507 0

#260000
0!
04

#270000
1!
14
b100 H
b100 K

#271000
b110 /
r-506 0

#280000
0!
04

#290000
1!
14
b101 H
b101 K

#291000
b111 /
r-505 0

#300000
0!
04

#310000
1!
14
b110 H
b110 K

#311000
b1000 /
r-504 0

#320000
0!
04

#330000
1!
14
b111 H
b111 K

#331000
b1001 /
r-503 0

#340000
0!
04

#350000
1!
14
b1000 H
b1000 K

#351000
b1010 /
r-502 0

#360000
0!
04

#370000
1!
14
b1001 H
b1001 K

#371000
b1011 /
r-501 0

#380000
0!
04

#390000
1!
14
b1010 H
b1010 K

#391000
b1100 /
r-500 0

#400000
0!
04

#410000
1!
14
b1011 H
b1011 K

#411000
b1101 /
r-499 0

#420000
0!
04

#430000
1!
14
b1100 H
b1100 K

#431000
b1110 /
r-498 0

#440000
0!
04

#450000
1!
14
b1101 H
b1101 K

#451000
b1111 /
r-497 0

#460000
0!
04

#470000
1!
14
b1110 H
b1110 K

#471000
b10000 /
r-496 0

#480000
0!
04

#490000
1!
14
b1111 H
b1111 K

#491000
b10001 /
r-495 0

#500000
0!
04

#510000
1!
14
b10000 H
b10000 K

#511000
b10010 /
r-494 0

#520000
0!
04

#530000
1!
14
b10001 H
b10001 K

#531000
b10011 /
r-493 0

#540000
0!
04

#550000
1!
14
b10010 H
b10010 K

#551000
b10100 /
r-492 0

#560000
0!
04

#570000
1!
14
b10011 H
b10011 K

#571000
b10101 /
r-491 0

#580000
0!
04

#590000
1!
14
b10100 H
b10100 K

#591000
b10110 /
r-490 0

#600000
0!
04

#610000
1!
14
b10101 H
b10101 K

#611000
b10111 /
r-489 0

#620000
0!
04

#630000
1!
14
b10110 H
b10110 K

#631000
b11000 /
r-488 0

#640000
0!
04

#650000
1!
14
b10111 H
b10111 K

#651000
b11001 /
r-487 0

#660000
0!
04

#670000
1!
14
b11000 H
b11000 K

#671000
b11010 /
r-486 0

#680000
0!
04

#690000
1!
14
b11001 H
b11001 K

#691000
b11011 /
r-485 0

#700000
0!
04

#710000
1!
14
b11010 H
b11010 K

#711000
b11100 /
r-484 0

#720000
0!
04

#730000
1!
14
b11011 H
b11011 K

#731000
b11101 /
r-483 0

#740000
0!
04

#750000
1!
14
b11100 H
b11100 K

#751000
b11110 /
r-482 0

#760000
0!
04

#770000
1!
14
b11101 H
b11101 K

#771000
b11111 /
r-481 0

#780000
0!
04

#790000
1!
14
b11110 H
b11110 K

#791000
b100000 /
r-480 0

#800000
0!
04

#810000
1!
14
b11111 H
b11111 K

#811000
b100001 /
r-479 0

#820000
0!
04

#830000
1!
14
b100000 H
b100000 K

#831000
b100010 /
r-478 0

#840000
0!
04

#850000
1!
14
b100001 H
b100001 K

#851000
b100011 /
r-477 0

#860000
0!
04

#870000
1!
14
b100010 H
b100010 K

#871000
b100100 /
r-476 0

#880000
0!
04

#890000
1!
14
b100011 H
b100011 K

#891000
b100101 /
r-475 0

#900000
0!
04

#910000
1!
14
b100100 H
b100100 K

#911000
b100110 /
r-474 0

#920000
0!
04

#930000
1!
14
b100101 H
b100101 K

#931000
b100111 /
r-473 0

#940000
0!
04

#950000
1!
14
b100110 H
b100110 K

#951000
b101000 /
r-472 0

#960000
0!
04

#970000
1!
14
b100111 H
b100111 K

#971000
b101001 /
r-471 0

#980000
0!
04

#990000
1!
14
b101000 H
b101000 K

#991000
b101010 /
r-470 0

